[{"buyBook": "[]", "exchangeId": 5, "sellBook": "[]", "updated": 1544497295000, "buyTotal": 0.0, "satoshiPrice": 0.0, "usdPrice": 0.0, "exchangeLogId": 5647168, "created": 1544497295000, "bestPair": "btc", "sellTotalBtc": 0.0, "volume": 0.6207, "activePairs": "btc", "sellTotal": 0.0, "volumeBtc": 0.0, "buyTotalBtc": 0.0, "coinId": 1}, {"buyBook": "[]", "exchangeId": 2, "sellBook": "[]", "updated": 1544499354000, "buyTotal": 10213393.4311, "satoshiPrice": 0.0126916378, "usdPrice": 4.29449486566e-07, "exchangeLogId": 5647523, "created": 1544499354000, "bestPair": "ltc", "sellTotalBtc": 3.4158442947, "volume": 248.49619017, "activePairs": "btc,ltc,doge", "sellTotal": 240.66769949, "volumeBtc": 3.21487966627, "buyTotalBtc": 3.28881967497, "coinId": 1}, {"buyBook": "[]", "exchangeId": 3, "sellBook": "[]", "updated": 1544499354000, "buyTotal": 143.897678406, "satoshiPrice": 0.01281578, "usdPrice": 4.33650111016e-07, "exchangeLogId": 5647524, "created": 1544499354000, "bestPair": "btc", "sellTotalBtc": 56.2266492929, "volume": 28.2350558804, "activePairs": "btc", "sellTotal": 64.9108615628, "volumeBtc": 0.0, "buyTotalBtc": 0.655180944369, "coinId": 1}, {"buyBook": "[]", "exchangeId": 4, "sellBook": "[]", "updated": 1544499355000, "buyTotal": 25050.6616024, "satoshiPrice": 0.01270001, "usdPrice": 4.29732778372e-07, "exchangeLogId": 5647525, "created": 1544499355000, "bestPair": "btc", "sellTotalBtc": 0.86048922516, "volume": 0.0, "activePairs": "btc", "sellTotal": 61.07382866, "volumeBtc": 1.01147305, "buyTotalBtc": 0.825775210418, "coinId": 1}, {"buyBook": "[]", "exchangeId": 10, "sellBook": "[]", "updated": 1544499366000, "buyTotal": 265591.542145, "satoshiPrice": 0.01250267, "usdPrice": 4.23055345324e-07, "exchangeLogId": 5647526, "created": 1544499366000, "bestPair": "btc", "sellTotalBtc": 121.670054888, "volume": 1666.71437071, "activePairs": "btc", "sellTotal": 691.27787214, "volumeBtc": 0.0, "buyTotalBtc": 1.31926221304, "coinId": 1}, {"buyBook": "[]", "exchangeId": 12, "sellBook": "[]", "updated": 1544499368000, "buyTotal": 10390.5375777, "satoshiPrice": 0.01273, "usdPrice": 4.30747556e-07, "exchangeLogId": 5647527, "created": 1544499368000, "bestPair": "btc", "sellTotalBtc": 0.452120226091, "volume": 0.0, "activePairs": "btc", "sellTotal": 27.28553565, "volumeBtc": 0.0828070049017, "buyTotalBtc": 0.259505078612, "coinId": 1}, {"buyBook": "[]", "exchangeId": 25, "sellBook": "[]", "updated": 1542387159000, "buyTotal": 0.0, "satoshiPrice": 0.0, "usdPrice": 0.0, "exchangeLogId": 4702887, "created": 1542387159000, "bestPair": "", "sellTotalBtc": 0.0, "volume": 0.0, "activePairs": "btc", "sellTotal": 0.0, "volumeBtc": 0.0, "buyTotalBtc": 0.0, "coinId": 1}, {"buyBook": "[]", "exchangeId": 20, "sellBook": "[]", "updated": 1544499370000, "buyTotal": 126.7043, "satoshiPrice": 0.012503038, "usdPrice": 4.23067797414e-07, "exchangeLogId": 5647528, "created": 1544499370000, "bestPair": "btc", "sellTotalBtc": 0.067015661504, "volume": 0.2904, "activePairs": "btc", "sellTotal": 4.1631, "volumeBtc": 0.0037752020328, "buyTotalBtc": 0.109677925159, "coinId": 1}, {"buyBook": "[]", "exchangeId": 21, "sellBook": "[]", "updated": 1544499371000, "buyTotal": 1780.85231878, "satoshiPrice": 0.481, "usdPrice": 1.62756932e-05, "exchangeLogId": 5647529, "created": 1544499371000, "bestPair": "eth", "sellTotalBtc": 26.5753074326, "volume": 3655.27963169, "activePairs": "btc,eth", "sellTotal": 1994.678642, "volumeBtc": 47.303278518, "buyTotalBtc": 21.9890895211, "coinId": 1}, {"buyBook": "[]", "exchangeId": 22, "sellBook": "[]", "updated": 1544499375000, "buyTotal": 0.022675, "satoshiPrice": 0.014, "usdPrice": 4.737208e-07, "exchangeLogId": 5647530, "created": 1544499375000, "bestPair": "BTC", "sellTotalBtc": 0.012, "volume": 0.0, "activePairs": "BTC", "sellTotal": 0.001, "volumeBtc": 0.0, "buyTotalBtc": 0.00031745, "coinId": 1}, {"buyBook": "[]", "exchangeId": 24, "sellBook": "[]", "updated": 1544499375000, "buyTotal": 0.0, "satoshiPrice": 0.0, "usdPrice": 0.0, "exchangeLogId": 5647531, "created": 1544499375000, "bestPair": "btc", "sellTotalBtc": 0.0, "volume": 0.0, "activePairs": "btc", "sellTotal": 0.0, "volumeBtc": 0.0, "buyTotalBtc": 0.0, "coinId": 1}, {"buyBook": "[]", "exchangeId": 26, "sellBook": "[]", "updated": 1543394185000, "buyTotal": 0.0, "satoshiPrice": 0.02269021, "usdPrice": 9.05623006625e-07, "exchangeLogId": 5137884, "created": 1543394185000, "bestPair": "btc", "sellTotalBtc": 0.0, "volume": 2559.40051283, "activePairs": "btc", "sellTotal": 0.0, "volumeBtc": 0.0, "buyTotalBtc": 0.0, "coinId": 1}, {"buyBook": "[]", "exchangeId": 5, "sellBook": "[]", "updated": 1544496876000, "buyTotal": 8.56e-06, "satoshiPrice": 4.4e-07, "usdPrice": 1.49116e-11, "exchangeLogId": 5646992, "created": 1544496876000, "bestPair": "btc", "sellTotalBtc": 0.11899454, "volume": 0.0, "activePairs": "btc", "sellTotal": 5.864e-05, "volumeBtc": 0.0, "buyTotalBtc": 0.25393224, "coinId": 2}, {"buyBook": "[]", "exchangeId": 22, "sellBook": "[]", "updated": 1544499439000, "buyTotal": 0.0, "satoshiPrice": 0.0, "usdPrice": 0.0, "exchangeLogId": 5647549, "created": 1544499439000, "bestPair": "", "sellTotalBtc": 0.0, "volume": 0.0, "activePairs": "", "sellTotal": 0.0, "volumeBtc": 0.0, "buyTotalBtc": 0.0, "coinId": 2}, {"buyBook": "[]", "exchangeId": 5, "sellBook": "[]", "updated": 1544496890000, "buyTotal": 1.42e-06, "satoshiPrice": 1.7e-07, "usdPrice": 5.7613e-12, "exchangeLogId": 5647000, "created": 1544496890000, "bestPair": "btc", "sellTotalBtc": 15.52410969, "volume": 0.1559, "activePairs": "btc", "sellTotal": 2.238e-05, "volumeBtc": 0.0, "buyTotalBtc": 1.79456563, "coinId": 3}, {"buyBook": "[]", "exchangeId": 12, "sellBook": "[]", "updated": 1544499465000, "buyTotal": 10843288.078, "satoshiPrice": 1.68e-07, "usdPrice": 5.6917392e-12, "exchangeLogId": 5647556, "created": 1544499465000, "bestPair": "btc", "sellTotalBtc": 921296.121203, "volume": 0.0, "activePairs": "btc", "sellTotal": 8987994.76898, "volumeBtc": 0.09309389624374434, "buyTotalBtc": 0.435979240348, "coinId": 3}, {"buyBook": "[]", "exchangeId": 2, "sellBook": "[]", "updated": 1544499537000, "buyTotal": 915276909.304, "satoshiPrice": 5e-07, "usdPrice": 1.69397e-11, "exchangeLogId": 5647568, "created": 1544499537000, "bestPair": "btc", "sellTotalBtc": 10.2298868513, "volume": 0.0, "activePairs": "btc,ltc,doge", "sellTotal": 359712.415936, "volumeBtc": 0.0, "buyTotalBtc": 0.0412773269684, "coinId": 4}, {"buyBook": "[]", "exchangeId": 4, "sellBook": "[]", "updated": 1544499538000, "buyTotal": 334389.332672, "satoshiPrice": 7e-07, "usdPrice": 2.371558e-11, "exchangeLogId": 5647569, "created": 1544499538000, "bestPair": "btc", "sellTotalBtc": 0.486339082367, "volume": 0.0, "activePairs": "btc", "sellTotal": 278318.376304, "volumeBtc": 0.01300352, "buyTotalBtc": 0.0509916946754, "coinId": 4}, {"buyBook": "[]", "exchangeId": 12, "sellBook": "[]", "updated": 1544499540000, "buyTotal": 1370550.522, "satoshiPrice": 2e-08, "usdPrice": 6.77588e-13, "exchangeLogId": 5647572, "created": 1544499540000, "bestPair": "btc", "sellTotalBtc": 2754.22176056, "volume": 0.0, "activePairs": "btc", "sellTotal": 1023923.84785, "volumeBtc": 5.994006e-08, "buyTotalBtc": 0.01909655044, "coinId": 5}, {"buyBook": "[]", "exchangeId": 2, "sellBook": "[]", "updated": 1544499554000, "buyTotal": 104275533.348, "satoshiPrice": 5e-08, "usdPrice": 1.69397e-12, "exchangeLogId": 5647576, "created": 1544499554000, "bestPair": "btc", "sellTotalBtc": 42.6282888106, "volume": 119254745.115, "activePairs": "btc,ltc,doge", "sellTotal": 134636882.861, "volumeBtc": 6.72401352044, "buyTotalBtc": 1.23061965427, "coinId": 6}, {"buyBook": "[]", "exchangeId": 11, "sellBook": "[]", "updated": 1544499555000, "buyTotal": 7697474.87533, "satoshiPrice": 3e-08, "usdPrice": 1.016382e-12, "exchangeLogId": 5647577, "created": 1544499555000, "bestPair": "btc", "sellTotalBtc": 9456.28870289, "volume": 4031365.99261, "activePairs": "btc", "sellTotal": 35565934.7461, "volumeBtc": 0.0, "buyTotalBtc": 0.138537647507, "coinId": 6}, {"buyBook": "[]", "exchangeId": 5, "sellBook": "[]", "updated": 1544496937000, "buyTotal": 0.0100351, "satoshiPrice": 0.00023904, "usdPrice": 8.1010656e-09, "exchangeLogId": 5647029, "created": 1544496937000, "bestPair": "btc", "sellTotalBtc": 2.01103932, "volume": 0.9792, "activePairs": "btc", "sellTotal": 0.01421144, "volumeBtc": 0.0, "buyTotalBtc": 1.66741009, "coinId": 7}, {"buyBook": "[]", "exchangeId": 3, "sellBook": "[]", "updated": 1544499556000, "buyTotal": 0.0, "satoshiPrice": 0.00023, "usdPrice": 7.792262e-09, "exchangeLogId": 5647578, "created": 1544499556000, "bestPair": "btc", "sellTotalBtc": 0.0, "volume": 0.0, "activePairs": "btc", "sellTotal": 0.0, "volumeBtc": 0.0, "buyTotalBtc": 0.0, "coinId": 7}, {"buyBook": "[]", "exchangeId": 4, "sellBook": "[]", "updated": 1544499556000, "buyTotal": 12000.1296373, "satoshiPrice": 0.00023851, "usdPrice": 8.080575694e-09, "exchangeLogId": 5647579, "created": 1544499556000, "bestPair": "btc", "sellTotalBtc": 1.46105564974, "volume": 0.0, "activePairs": "btc", "sellTotal": 5770.64070295, "volumeBtc": 2.86457409, "buyTotalBtc": 2.7169153008, "coinId": 7}, {"buyBook": "[]", "exchangeId": 20, "sellBook": "[]", "updated": 1544499578000, "buyTotal": 7085992.4421, "satoshiPrice": 1e-09, "usdPrice": 3.38794e-14, "exchangeLogId": 5647581, "created": 1544499578000, "bestPair": "btc", "sellTotalBtc": 114.270434307, "volume": 0.0, "activePairs": "btc", "sellTotal": 20489383.8222, "volumeBtc": 0.0, "buyTotalBtc": 0.0070859924421, "coinId": 8}, {"buyBook": "[]", "exchangeId": 1, "sellBook": "[]", "updated": 1544499593000, "buyTotal": 724339.67, "satoshiPrice": 1.85e-06, "usdPrice": 6.267689e-11, "exchangeLogId": 5647585, "created": 1544499593000, "bestPair": "btc", "sellTotalBtc": 0.3803170147, "volume": 15219389.85, "activePairs": "btc", "sellTotal": 200758.99, "volumeBtc": 28.90148422, "buyTotalBtc": 1.3262430677, "coinId": 9}, {"buyBook": "[]", "exchangeId": 2, "sellBook": "[]", "updated": 1544499594000, "buyTotal": 17070482.303, "satoshiPrice": 1.91111273275e-06, "usdPrice": 6.4747352718e-11, "exchangeLogId": 5647586, "created": 1544499594000, "bestPair": "ltc", "sellTotalBtc": 24.1419898086, "volume": 10346550.5306, "activePairs": "btc,ltc,doge", "sellTotal": 10374356.2489, "volumeBtc": 19.8886071518, "buyTotalBtc": 24.4541160416, "coinId": 9}, {"buyBook": "[]", "exchangeId": 4, "sellBook": "[]", "updated": 1544499594000, "buyTotal": 1259829.3292, "satoshiPrice": 1.87e-06, "usdPrice": 6.3354478e-11, "exchangeLogId": 5647587, "created": 1544499594000, "bestPair": "btc", "sellTotalBtc": 0.809734126144, "volume": 0.0, "activePairs": "btc", "sellTotal": 401116.09607, "volumeBtc": 0.92743245, "buyTotalBtc": 0.655565035646, "coinId": 9}, {"buyBook": "[]", "exchangeId": 23, "sellBook": "[]", "updated": 1544499596000, "buyTotal": 0.0, "satoshiPrice": 0.0, "usdPrice": 0.0, "exchangeLogId": 5647588, "created": 1544499596000, "bestPair": "btc", "sellTotalBtc": 0.0, "volume": 0.0, "activePairs": "btc,ltc", "sellTotal": 0.0, "volumeBtc": 0.0, "buyTotalBtc": 0.0, "coinId": 9}, {"buyBook": "[]", "exchangeId": 4, "sellBook": "[]", "updated": 1544499598000, "buyTotal": 3777187.073, "satoshiPrice": 2e-08, "usdPrice": 6.77588e-13, "exchangeLogId": 5647591, "created": 1544499598000, "bestPair": "btc", "sellTotalBtc": 0.317727505313, "volume": 0.0, "activePairs": "btc", "sellTotal": 3504222.00047, "volumeBtc": 0.0, "buyTotalBtc": 0.0446654015, "coinId": 10}, {"buyBook": "[]", "exchangeId": 5, "sellBook": "[]", "updated": 1544497004000, "buyTotal": 2.703e-05, "satoshiPrice": 1.74e-06, "usdPrice": 5.89686e-11, "exchangeLogId": 5647049, "created": 1544497004000, "bestPair": "btc", "sellTotalBtc": 0.36696075, "volume": 0.0592, "activePairs": "btc", "sellTotal": 0.0001479, "volumeBtc": 0.0, "buyTotalBtc": 0.09046368, "coinId": 12}, {"buyBook": "[]", "exchangeId": 2, "sellBook": "[]", "updated": 1544499605000, "buyTotal": 413614123.929, "satoshiPrice": 1.79e-06, "usdPrice": 6.0644126e-11, "exchangeLogId": 5647596, "created": 1544499605000, "bestPair": "btc", "sellTotalBtc": 7.3291122073, "volume": 1489852.23593, "activePairs": "btc,ltc,doge", "sellTotal": 1220801.69834, "volumeBtc": 2.69746284814, "buyTotalBtc": 0.938693031536, "coinId": 12}, {"buyBook": "[]", "exchangeId": 4, "sellBook": "[]", "updated": 1544499606000, "buyTotal": 2923527.64969, "satoshiPrice": 1.82e-06, "usdPrice": 6.1660508e-11, "exchangeLogId": 5647597, "created": 1544499606000, "bestPair": "btc", "sellTotalBtc": 0.930865967396, "volume": 0.0, "activePairs": "btc", "sellTotal": 475836.960282, "volumeBtc": 1.78638762, "buyTotalBtc": 4.57428916112, "coinId": 12}, {"buyBook": "[]", "exchangeId": 25, "sellBook": "[]", "updated": 1544499616000, "buyTotal": 0.0, "satoshiPrice": 0.0, "usdPrice": 0.0, "exchangeLogId": 5647598, "created": 1544499616000, "bestPair": "", "sellTotalBtc": 0.0, "volume": 0.0, "activePairs": "btc", "sellTotal": 0.0, "volumeBtc": 0.0, "buyTotalBtc": 0.0, "coinId": 12}, {"buyBook": "[]", "exchangeId": 4, "sellBook": "[]", "updated": 1544499206000, "buyTotal": 447514.208018, "satoshiPrice": 8.91e-06, "usdPrice": 3.01489452e-10, "exchangeLogId": 5647499, "created": 1544499206000, "bestPair": "btc", "sellTotalBtc": 0.370484013009, "volume": 0.0, "activePairs": "btc", "sellTotal": 38592.7742099, "volumeBtc": 1.18748751, "buyTotalBtc": 1.94088646468, "coinId": 13}, {"buyBook": "[]", "exchangeId": 21, "sellBook": "[]", "updated": 1544499208000, "buyTotal": 1208079.06993, "satoshiPrice": 8.85e-06, "usdPrice": 2.9945922e-10, "exchangeLogId": 5647500, "created": 1544499208000, "bestPair": "btc", "sellTotalBtc": 7.13487341231, "volume": 939205.126825, "activePairs": "btc", "sellTotal": 717788.116963, "volumeBtc": 8.03349298, "buyTotalBtc": 10.0671415907, "coinId": 13}, {"buyBook": "[]", "exchangeId": 10, "sellBook": "[]", "updated": 1544295260000, "buyTotal": 989846.120076, "satoshiPrice": 8.04e-06, "usdPrice": 2.70615144e-10, "exchangeLogId": 5538780, "created": 1544295260000, "bestPair": "btc", "sellTotalBtc": 106.420706755, "volume": 18308.0718796, "activePairs": "btc", "sellTotal": 731903.240182, "volumeBtc": 0.0, "buyTotalBtc": 0.356898334654, "coinId": 13}, {"buyBook": "[]", "exchangeId": 4, "sellBook": "[]", "updated": 1544499639000, "buyTotal": 1198728.34454, "satoshiPrice": 1.62e-06, "usdPrice": 5.4884628e-11, "exchangeLogId": 5647606, "created": 1544499639000, "bestPair": "btc", "sellTotalBtc": 0.289288296958, "volume": 0.0, "activePairs": "btc", "sellTotal": 111747.556887, "volumeBtc": 0.03039264, "buyTotalBtc": 0.400805819104, "coinId": 14}, {"buyBook": "[]", "exchangeId": 12, "sellBook": "[]", "updated": 1544499640000, "buyTotal": 90332.0, "satoshiPrice": 1.8e-06, "usdPrice": 6.098292e-11, "exchangeLogId": 5647607, "created": 1544499640000, "bestPair": "btc", "sellTotalBtc": 4.74306628829, "volume": 0.0, "activePairs": "btc", "sellTotal": 21813.8121878, "volumeBtc": 0.00041586193806, "buyTotalBtc": 0.0193739, "coinId": 14}, {"buyBook": "[]", "exchangeId": 17, "sellBook": "[]", "updated": 1544499641000, "buyTotal": 0.0, "satoshiPrice": 0.0, "usdPrice": 0.0, "exchangeLogId": 5647608, "created": 1544499641000, "bestPair": "btc", "sellTotalBtc": 0.0, "volume": 0.0, "activePairs": "btc", "sellTotal": 0.0, "volumeBtc": 0.0, "buyTotalBtc": 0.0, "coinId": 14}, {"buyBook": "[]", "exchangeId": 26, "sellBook": "[]", "updated": 1544499641000, "buyTotal": 0.0, "satoshiPrice": 2e-07, "usdPrice": 6.77588e-12, "exchangeLogId": 5647609, "created": 1544499641000, "bestPair": "btc", "sellTotalBtc": 0.0, "volume": 0.0, "activePairs": "btc", "sellTotal": 0.0, "volumeBtc": 0.0, "buyTotalBtc": 0.0, "coinId": 14}, {"buyBook": "[]", "exchangeId": 12, "sellBook": "[]", "updated": 1543677348000, "buyTotal": 204241.84496, "satoshiPrice": 4.89e-06, "usdPrice": 2.02473384e-10, "exchangeLogId": 5260204, "created": 1543677348000, "bestPair": "btc", "sellTotalBtc": 49.5475654835, "volume": 0.0, "activePairs": "btc", "sellTotal": 35763.2193806, "volumeBtc": 0.0163153972027625, "buyTotalBtc": 0.0203389899998, "coinId": 15}, {"buyBook": "[]", "exchangeId": 4, "sellBook": "[]", "updated": 1544499642000, "buyTotal": 0.0, "satoshiPrice": 0.0, "usdPrice": 0.0, "exchangeLogId": 5647610, "created": 1544499642000, "bestPair": "", "sellTotalBtc": 0.0, "volume": 0.0, "activePairs": "", "sellTotal": 0.0, "volumeBtc": 0.0, "buyTotalBtc": 0.0, "coinId": 15}, {"buyBook": "[]", "exchangeId": 17, "sellBook": "[]", "updated": 1544499650000, "buyTotal": 0.0, "satoshiPrice": 0.0, "usdPrice": 0.0, "exchangeLogId": 5647616, "created": 1544499650000, "bestPair": "btc", "sellTotalBtc": 0.0, "volume": 0.0, "activePairs": "btc", "sellTotal": 0.0, "volumeBtc": 0.0, "buyTotalBtc": 0.0, "coinId": 18}, {"buyBook": "[]", "exchangeId": 2, "sellBook": "[]", "updated": 1544499645000, "buyTotal": 1638356498.78, "satoshiPrice": 1.708e-05, "usdPrice": 5.78660152e-10, "exchangeLogId": 5647612, "created": 1544499645000, "bestPair": "btc", "sellTotalBtc": 17.804793124, "volume": 2368.415076, "activePairs": "btc,ltc,doge", "sellTotal": 18708.4614908, "volumeBtc": 0.0405330078072, "buyTotalBtc": 0.366173233225, "coinId": 18}, {"buyBook": "[]", "exchangeId": 4, "sellBook": "[]", "updated": 1544499646000, "buyTotal": 23526.1504335, "satoshiPrice": 1.45e-05, "usdPrice": 4.912513e-10, "exchangeLogId": 5647613, "created": 1544499646000, "bestPair": "btc", "sellTotalBtc": 1.55541357789, "volume": 0.0, "activePairs": "btc", "sellTotal": 8291.57981811, "volumeBtc": 0.02280122, "buyTotalBtc": 0.0229304165327, "coinId": 18}, {"buyBook": "[]", "exchangeId": 10, "sellBook": "[]", "updated": 1544499648000, "buyTotal": 78902.5739266, "satoshiPrice": 1.71e-05, "usdPrice": 5.7933774e-10, "exchangeLogId": 5647614, "created": 1544499648000, "bestPair": "btc", "sellTotalBtc": 14.3391260519, "volume": 12.0082808, "activePairs": "btc", "sellTotal": 6541.91799687, "volumeBtc": 0.0, "buyTotalBtc": 0.482544789774, "coinId": 18}, {"buyBook": "[]", "exchangeId": 12, "sellBook": "[]", "updated": 1544499649000, "buyTotal": 74822.353244, "satoshiPrice": 1.65e-05, "usdPrice": 5.590101e-10, "exchangeLogId": 5647615, "created": 1544499649000, "bestPair": "btc", "sellTotalBtc": 0.547738871186, "volume": 0.0, "activePairs": "btc", "sellTotal": 3263.75535513, "volumeBtc": 0.0010635340191612, "buyTotalBtc": 0.0322435556925, "coinId": 18}, {"buyBook": "[]", "exchangeId": 2, "sellBook": "[]", "updated": 1544499726000, "buyTotal": 7875856.40334, "satoshiPrice": 4.099e-05, "usdPrice": 1.388716606e-09, "exchangeLogId": 5647629, "created": 1544499726000, "bestPair": "btc", "sellTotalBtc": 3.94215415467, "volume": 729.6075442, "activePairs": "btc,ltc,doge", "sellTotal": 21451.1241895, "volumeBtc": 0.02983273, "buyTotalBtc": 0.554972838546, "coinId": 19}, {"buyBook": "[]", "exchangeId": 3, "sellBook": "[]", "updated": 1544499727000, "buyTotal": 111319.86719, "satoshiPrice": 4.175e-05, "usdPrice": 1.41446495e-09, "exchangeLogId": 5647630, "created": 1544499727000, "bestPair": "btc", "sellTotalBtc": 1.28086177021, "volume": 0.0, "activePairs": "btc", "sellTotal": 8682.26930514, "volumeBtc": 0.0, "buyTotalBtc": 0.167466019799, "coinId": 19}, {"buyBook": "[]", "exchangeId": 4, "sellBook": "[]", "updated": 1544499728000, "buyTotal": 61849.1887538, "satoshiPrice": 4.102e-05, "usdPrice": 1.389732988e-09, "exchangeLogId": 5647631, "created": 1544499728000, "bestPair": "btc", "sellTotalBtc": 1.05754214432, "volume": 0.0, "activePairs": "btc", "sellTotal": 22515.4767162, "volumeBtc": 0.89660975, "buyTotalBtc": 1.29329677503, "coinId": 19}, {"buyBook": "[]", "exchangeId": 12, "sellBook": "[]", "updated": 1544499738000, "buyTotal": 108735.768761, "satoshiPrice": 4.511e-05, "usdPrice": 1.528299734e-09, "exchangeLogId": 5647632, "created": 1544499738000, "bestPair": "btc", "sellTotalBtc": 1.97035143078, "volume": 0.0, "activePairs": "btc", "sellTotal": 230.27205254, "volumeBtc": 0.0, "buyTotalBtc": 0.0323066354558, "coinId": 19}, {"buyBook": "[]", "exchangeId": 5, "sellBook": "[]", "updated": 1544497091000, "buyTotal": 0.0, "satoshiPrice": 0.0, "usdPrice": 0.0, "exchangeLogId": 5647087, "created": 1544497091000, "bestPair": "btc", "sellTotalBtc": 0.0, "volume": 0.0001, "activePairs": "btc", "sellTotal": 0.0, "volumeBtc": 0.0, "buyTotalBtc": 0.0, "coinId": 19}, {"buyBook": "[]", "exchangeId": 4, "sellBook": "[]", "updated": 1544498994000, "buyTotal": 3617451.7671, "satoshiPrice": 3.4e-07, "usdPrice": 1.1504648e-11, "exchangeLogId": 5647463, "created": 1544498994000, "bestPair": "btc", "sellTotalBtc": 0.953106814004, "volume": 0.0, "activePairs": "btc", "sellTotal": 1206146.1908, "volumeBtc": 0.0, "buyTotalBtc": 0.32466067352, "coinId": 20}, {"buyBook": "[]", "exchangeId": 4, "sellBook": "[]", "updated": 1544499123000, "buyTotal": 52735112.1004, "satoshiPrice": 2e-08, "usdPrice": 6.76744e-13, "exchangeLogId": 5647469, "created": 1544499123000, "bestPair": "btc", "sellTotalBtc": 0.712889136786, "volume": 0.0, "activePairs": "btc", "sellTotal": 15695576.298, "volumeBtc": 0.00240548, "buyTotalBtc": 0.62076197197, "coinId": 21}, {"buyBook": "[]", "exchangeId": 12, "sellBook": "[]", "updated": 1544499133000, "buyTotal": 3101114.0, "satoshiPrice": 2e-08, "usdPrice": 6.76744e-13, "exchangeLogId": 5647470, "created": 1544499133000, "bestPair": "btc", "sellTotalBtc": 657.324862114, "volume": 0.0, "activePairs": "btc", "sellTotal": 6184732.0181, "volumeBtc": 0.0018284885914085, "buyTotalBtc": 0.04372354, "coinId": 21}, {"buyBook": "[]", "exchangeId": 17, "sellBook": "[]", "updated": 1544499135000, "buyTotal": 10586.8, "satoshiPrice": 1e-08, "usdPrice": 3.38372e-13, "exchangeLogId": 5647471, "created": 1544499135000, "bestPair": "btc", "sellTotalBtc": 0.0, "volume": 0.0, "activePairs": "btc", "sellTotal": 0.0, "volumeBtc": 0.0, "buyTotalBtc": 0.000105868, "coinId": 21}, {"buyBook": "[]", "exchangeId": 12, "sellBook": "[]", "updated": 1544499153000, "buyTotal": 5482486585.92, "satoshiPrice": 2e-10, "usdPrice": 6.76744e-15, "exchangeLogId": 5647476, "created": 1544499153000, "bestPair": "btc", "sellTotalBtc": 627831381383.0, "volume": 0.0, "activePairs": "btc", "sellTotal": 4258679624.05, "volumeBtc": 0.03456107625244755, "buyTotalBtc": 0.60062254874, "coinId": 23}, {"buyBook": "[]", "exchangeId": 4, "sellBook": "[]", "updated": 1544499164000, "buyTotal": 6048756.50242, "satoshiPrice": 9.1e-07, "usdPrice": 3.0791852e-11, "exchangeLogId": 5647479, "created": 1544499164000, "bestPair": "btc", "sellTotalBtc": 0.178607883464, "volume": 0.0, "activePairs": "btc", "sellTotal": 102994.141496, "volumeBtc": 0.00767034, "buyTotalBtc": 0.235702310109, "coinId": 24}, {"buyBook": "[]", "exchangeId": 22, "sellBook": "[]", "updated": 1544499168000, "buyTotal": 10.6909090909, "satoshiPrice": 1.1e-06, "usdPrice": 3.722092e-11, "exchangeLogId": 5647480, "created": 1544499168000, "bestPair": "BTC", "sellTotalBtc": 0.00172415, "volume": 0.0, "activePairs": "BTC", "sellTotal": 523.919354839, "volumeBtc": 0.0, "buyTotalBtc": 1.176e-05, "coinId": 24}, {"buyBook": "[]", "exchangeId": 25, "sellBook": "[]", "updated": 1544499169000, "buyTotal": 0.0, "satoshiPrice": 0.0, "usdPrice": 0.0, "exchangeLogId": 5647481, "created": 1544499169000, "bestPair": "", "sellTotalBtc": 0.0, "volume": 0.0, "activePairs": "btc", "sellTotal": 0.0, "volumeBtc": 0.0, "buyTotalBtc": 0.0, "coinId": 24}, {"buyBook": "[]", "exchangeId": 2, "sellBook": "[]", "updated": 1544499179000, "buyTotal": 1085041735.6, "satoshiPrice": 1.311e-05, "usdPrice": 4.43605692e-10, "exchangeLogId": 5647488, "created": 1544499179000, "bestPair": "btc", "sellTotalBtc": 3.20078668598, "volume": 19078.6324101, "activePairs": "btc,ltc,doge", "sellTotal": 55737.547947, "volumeBtc": 0.269844530622, "buyTotalBtc": 1.49472347978, "coinId": 26}, {"buyBook": "[]", "exchangeId": 4, "sellBook": "[]", "updated": 1544499179000, "buyTotal": 1270057.50559, "satoshiPrice": 1.279e-05, "usdPrice": 4.32777788e-10, "exchangeLogId": 5647489, "created": 1544499179000, "bestPair": "btc", "sellTotalBtc": 0.822476095929, "volume": 0.0, "activePairs": "btc", "sellTotal": 51812.5820505, "volumeBtc": 0.16239878, "buyTotalBtc": 0.359920670184, "coinId": 26}, {"buyBook": "[]", "exchangeId": 10, "sellBook": "[]", "updated": 1544499181000, "buyTotal": 601634.014232, "satoshiPrice": 1.3e-05, "usdPrice": 4.398836e-10, "exchangeLogId": 5647490, "created": 1544499181000, "bestPair": "btc", "sellTotalBtc": 24.229033647, "volume": 722.41600452, "activePairs": "btc", "sellTotal": 8903.8430621, "volumeBtc": 0.0, "buyTotalBtc": 0.148527718168, "coinId": 26}, {"buyBook": "[]", "exchangeId": 5, "sellBook": "[]", "updated": 1544497240000, "buyTotal": 0.0, "satoshiPrice": 0.0, "usdPrice": 0.0, "exchangeLogId": 5647132, "created": 1544497240000, "bestPair": "btc", "sellTotalBtc": 0.0, "volume": 0.0, "activePairs": "btc", "sellTotal": 0.0, "volumeBtc": 0.0, "buyTotalBtc": 0.0, "coinId": 27}, {"buyBook": "[]", "exchangeId": 3, "sellBook": "[]", "updated": 1544499182000, "buyTotal": 21550223.6255, "satoshiPrice": 3e-08, "usdPrice": 1.015116e-12, "exchangeLogId": 5647491, "created": 1544499182000, "bestPair": "btc", "sellTotalBtc": 1.71697581765, "volume": 463577.281092, "activePairs": "btc", "sellTotal": 11724081.7513, "volumeBtc": 0.0, "buyTotalBtc": 0.267595966291, "coinId": 27}, {"buyBook": "[]", "exchangeId": 11, "sellBook": "[]", "updated": 1544499200000, "buyTotal": 909229.316667, "satoshiPrice": 3e-08, "usdPrice": 1.015116e-12, "exchangeLogId": 5647492, "created": 1544499200000, "bestPair": "btc", "sellTotalBtc": 372.529391406, "volume": 1835.0, "activePairs": "btc", "sellTotal": 8869157.01377, "volumeBtc": 0.0, "buyTotalBtc": 0.011038493, "coinId": 27}, {"buyBook": "[]", "exchangeId": 11, "sellBook": "[]", "updated": 1544499203000, "buyTotal": 1186267.90642, "satoshiPrice": 4.3e-07, "usdPrice": 1.4549996e-11, "exchangeLogId": 5647496, "created": 1544499203000, "bestPair": "btc", "sellTotalBtc": 60.1813500496, "volume": 15.0, "activePairs": "btc", "sellTotal": 321680.174857, "volumeBtc": 0.0, "buyTotalBtc": 0.03426356, "coinId": 28}, {"buyBook": "[]", "exchangeId": 4, "sellBook": "[]", "updated": 1544499204000, "buyTotal": 378530590.45, "satoshiPrice": 1.05438382717e-08, "usdPrice": 3.56773964367e-13, "exchangeLogId": 5647497, "created": 1544499204000, "bestPair": "ltc", "sellTotalBtc": 4.43330701141, "volume": 0.0, "activePairs": "btc,ltc", "sellTotal": 284602339.659, "volumeBtc": 0.01624036, "buyTotalBtc": 3.80877615348, "coinId": 29}, {"buyBook": "[]", "exchangeId": 7, "sellBook": "[]", "updated": 1544499205000, "buyTotal": 75142840.271, "satoshiPrice": 1e-08, "usdPrice": 3.38372e-13, "exchangeLogId": 5647498, "created": 1544499205000, "bestPair": "btc", "sellTotalBtc": 9776.40061794, "volume": 549.5, "activePairs": "btc", "sellTotal": 194428251.618, "volumeBtc": 1.099e-05, "buyTotalBtc": 0.75142840271, "coinId": 29}, {"buyBook": "[]", "exchangeId": 4, "sellBook": "[]", "updated": 1544499318000, "buyTotal": 3358699.95237, "satoshiPrice": 4.7e-07, "usdPrice": 1.5903484e-11, "exchangeLogId": 5647510, "created": 1544499318000, "bestPair": "btc", "sellTotalBtc": 0.451662227671, "volume": 0.0, "activePairs": "btc", "sellTotal": 575328.503865, "volumeBtc": 0.01098169, "buyTotalBtc": 0.244613237555, "coinId": 30}, {"buyBook": "[]", "exchangeId": 17, "sellBook": "[]", "updated": 1544499320000, "buyTotal": 0.0, "satoshiPrice": 0.0, "usdPrice": 0.0, "exchangeLogId": 5647511, "created": 1544499320000, "bestPair": "btc", "sellTotalBtc": 0.0, "volume": 0.0, "activePairs": "btc", "sellTotal": 0.0, "volumeBtc": 0.0, "buyTotalBtc": 0.0, "coinId": 30}, {"buyBook": "[]", "exchangeId": 4, "sellBook": "[]", "updated": 1544499341000, "buyTotal": 20466.8368004, "satoshiPrice": 0.00023436, "usdPrice": 7.930086192e-09, "exchangeLogId": 5647519, "created": 1544499341000, "bestPair": "btc", "sellTotalBtc": 0.994768244884, "volume": 0.0, "activePairs": "btc", "sellTotal": 4052.11871094, "volumeBtc": 1.96728665, "buyTotalBtc": 4.19484731475, "coinId": 31}, {"buyBook": "[]", "exchangeId": 21, "sellBook": "[]", "updated": 1544499341000, "buyTotal": 84211.8128266, "satoshiPrice": 0.00023732, "usdPrice": 8.030244304e-09, "exchangeLogId": 5647520, "created": 1544499341000, "bestPair": "btc", "sellTotalBtc": 11.2311436002, "volume": 41050.7292538, "activePairs": "btc", "sellTotal": 43229.4549076, "volumeBtc": 9.89176077, "buyTotalBtc": 19.0490683261, "coinId": 31}, {"buyBook": "[]", "exchangeId": 2, "sellBook": "[]", "updated": 1544499342000, "buyTotal": 52218316.596, "satoshiPrice": 7.59872602426e-07, "usdPrice": 2.57119612228e-11, "exchangeLogId": 5647521, "created": 1544499342000, "bestPair": "doge", "sellTotalBtc": 10.9393124465, "volume": 22763.8703428, "activePairs": "btc,ltc,doge", "sellTotal": 264843.787339, "volumeBtc": 0.0163356490807, "buyTotalBtc": 0.202918043565, "coinId": 32}, {"buyBook": "[]", "exchangeId": 4, "sellBook": "[]", "updated": 1544499384000, "buyTotal": 68648554.6015, "satoshiPrice": 5.81680205323e-08, "usdPrice": 1.96824294436e-12, "exchangeLogId": 5647538, "created": 1544499384000, "bestPair": "ltc", "sellTotalBtc": 1.506455308, "volume": 0.0, "activePairs": "btc,ltc", "sellTotal": 21665789.9915, "volumeBtc": 3.65036509, "buyTotalBtc": 3.41627338262, "coinId": 33}, {"buyBook": "[]", "exchangeId": 12, "sellBook": "[]", "updated": 1544499385000, "buyTotal": 28569471.606, "satoshiPrice": 6e-08, "usdPrice": 2.030232e-12, "exchangeLogId": 5647539, "created": 1544499385000, "bestPair": "btc", "sellTotalBtc": 17249121.1888, "volume": 0.0, "activePairs": "btc", "sellTotal": 97784785.3127, "volumeBtc": 0.0427680163636367, "buyTotalBtc": 0.94790546424, "coinId": 33}, {"buyBook": "[]", "exchangeId": 5, "sellBook": "[]", "updated": 1544497328000, "buyTotal": 0.0, "satoshiPrice": 0.0, "usdPrice": 0.0, "exchangeLogId": 5647184, "created": 1544497328000, "bestPair": "btc", "sellTotalBtc": 0.0, "volume": 0.0, "activePairs": "btc", "sellTotal": 0.0, "volumeBtc": 0.0, "buyTotalBtc": 0.0, "coinId": 34}, {"buyBook": "[]", "exchangeId": 4, "sellBook": "[]", "updated": 1544499385000, "buyTotal": 69095621.921, "satoshiPrice": 1e-08, "usdPrice": 3.38372e-13, "exchangeLogId": 5647540, "created": 1544499385000, "bestPair": "btc", "sellTotalBtc": 1.10791739468, "volume": 0.0, "activePairs": "btc", "sellTotal": 30781338.4234, "volumeBtc": 0.01412051, "buyTotalBtc": 0.69095621921, "coinId": 34}, {"buyBook": "[]", "exchangeId": 4, "sellBook": "[]", "updated": 1544499771000, "buyTotal": 2679522378.85, "satoshiPrice": 2.83096357109e-10, "usdPrice": 9.59113472104e-15, "exchangeLogId": 5647640, "created": 1544499771000, "bestPair": "ltc", "sellTotalBtc": 0.388742412675, "volume": 0.0, "activePairs": "ltc", "sellTotal": 901255067.805, "volumeBtc": 0.0, "buyTotalBtc": 0.662456382392, "coinId": 36}, {"buyBook": "[]", "exchangeId": 17, "sellBook": "[]", "updated": 1544499790000, "buyTotal": 0.0, "satoshiPrice": 0.0, "usdPrice": 0.0, "exchangeLogId": 5647641, "created": 1544499790000, "bestPair": "btc", "sellTotalBtc": 0.486694923377, "volume": 0.0, "activePairs": "btc", "sellTotal": 9886185.24386, "volumeBtc": 0.0, "buyTotalBtc": 0.0, "coinId": 36}, {"buyBook": "[]", "exchangeId": 5, "sellBook": "[]", "updated": 1544497144000, "buyTotal": 0.0, "satoshiPrice": 0.0, "usdPrice": 0.0, "exchangeLogId": 5647099, "created": 1544497144000, "bestPair": "btc", "sellTotalBtc": 0.0, "volume": 0.0, "activePairs": "btc", "sellTotal": 0.0, "volumeBtc": 0.0, "buyTotalBtc": 0.0, "coinId": 36}, {"buyBook": "[]", "exchangeId": 4, "sellBook": "[]", "updated": 1544499768000, "buyTotal": 534766.107002, "satoshiPrice": 1.7e-06, "usdPrice": 5.759498e-11, "exchangeLogId": 5647637, "created": 1544499768000, "bestPair": "btc", "sellTotalBtc": 0.719543387855, "volume": 0.0, "activePairs": "btc", "sellTotal": 343886.628158, "volumeBtc": 0.42493958, "buyTotalBtc": 0.42400263712, "coinId": 37}, {"buyBook": "[]", "exchangeId": 12, "sellBook": "[]", "updated": 1544499768000, "buyTotal": 495170.983737, "satoshiPrice": 1.69e-06, "usdPrice": 5.7256186e-11, "exchangeLogId": 5647638, "created": 1544499768000, "bestPair": "btc", "sellTotalBtc": 459.063183841, "volume": 0.0, "activePairs": "btc", "sellTotal": 846363.301067, "volumeBtc": 0.460701782754261, "buyTotalBtc": 0.417351350303, "coinId": 37}, {"buyBook": "[]", "exchangeId": 17, "sellBook": "[]", "updated": 1544499770000, "buyTotal": 1752.74075282, "satoshiPrice": 2.5e-07, "usdPrice": 8.46985e-12, "exchangeLogId": 5647639, "created": 1544499770000, "bestPair": "btc", "sellTotalBtc": 0.0716388902327, "volume": 0.0, "activePairs": "btc", "sellTotal": 1390.12777428, "volumeBtc": 0.0, "buyTotalBtc": 0.000438185188205, "coinId": 37}, {"buyBook": "[]", "exchangeId": 5, "sellBook": "[]", "updated": 1544496897000, "buyTotal": 1.648e-05, "satoshiPrice": 1.07e-06, "usdPrice": 3.62623e-11, "exchangeLogId": 5647006, "created": 1544496897000, "bestPair": "btc", "sellTotalBtc": 0.12534795, "volume": 0.0271, "activePairs": "btc", "sellTotal": 0.00011391, "volumeBtc": 0.0, "buyTotalBtc": 0.07458254, "coinId": 42}, {"buyBook": "[]", "exchangeId": 12, "sellBook": "[]", "updated": 1544499498000, "buyTotal": 95477.2542703, "satoshiPrice": 1.21e-06, "usdPrice": 4.0994074e-11, "exchangeLogId": 5647560, "created": 1544499498000, "bestPair": "btc", "sellTotalBtc": 166.611257519, "volume": 0.0, "activePairs": "btc", "sellTotal": 29034.8976855, "volumeBtc": 0.0359291562361936, "buyTotalBtc": 0.03768377616, "coinId": 42}, {"buyBook": "[]", "exchangeId": 5, "sellBook": "[]", "updated": 1544496969000, "buyTotal": 3e-08, "satoshiPrice": 2e-08, "usdPrice": 6.778e-13, "exchangeLogId": 5647033, "created": 1544496969000, "bestPair": "btc", "sellTotalBtc": 6.84541516, "volume": 1.0533, "activePairs": "btc", "sellTotal": 1.375e-05, "volumeBtc": 0.0, "buyTotalBtc": 0.41397409, "coinId": 43}, {"buyBook": "[]", "exchangeId": 12, "sellBook": "[]", "updated": 1544499590000, "buyTotal": 9944538.0, "satoshiPrice": 1e-08, "usdPrice": 3.38794e-13, "exchangeLogId": 5647583, "created": 1544499590000, "bestPair": "btc", "sellTotalBtc": 7429.88469746, "volume": 0.0, "activePairs": "btc", "sellTotal": 15133836.6987, "volumeBtc": 0.00021159000999, "buyTotalBtc": 0.09944538, "coinId": 43}, {"buyBook": "[]", "exchangeId": 17, "sellBook": "[]", "updated": 1544499592000, "buyTotal": 0.0, "satoshiPrice": 0.0, "usdPrice": 0.0, "exchangeLogId": 5647584, "created": 1544499592000, "bestPair": "btc", "sellTotalBtc": 0.0, "volume": 0.0, "activePairs": "btc", "sellTotal": 0.0, "volumeBtc": 0.0, "buyTotalBtc": 0.0, "coinId": 43}, {"buyBook": "[]", "exchangeId": 12, "sellBook": "[]", "updated": 1544499502000, "buyTotal": 349778.0, "satoshiPrice": 3e-08, "usdPrice": 1.016382e-12, "exchangeLogId": 5647562, "created": 1544499502000, "bestPair": "btc", "sellTotalBtc": 55590005.8785, "volume": 0.0, "activePairs": "btc", "sellTotal": 617401.437562, "volumeBtc": 0.0002884, "buyTotalBtc": 0.00543712, "coinId": 44}, {"buyBook": "[]", "exchangeId": 4, "sellBook": "[]", "updated": 1544499467000, "buyTotal": 55844907.3363, "satoshiPrice": 3e-08, "usdPrice": 1.016382e-12, "exchangeLogId": 5647558, "created": 1544499467000, "bestPair": "btc", "sellTotalBtc": 0.179273892452, "volume": 0.0, "activePairs": "btc", "sellTotal": 2166562.66456, "volumeBtc": 0.0046235, "buyTotalBtc": 0.647178716925, "coinId": 49}, {"buyBook": "[]", "exchangeId": 4, "sellBook": "[]", "updated": 1544499316000, "buyTotal": 2332786227.4, "satoshiPrice": 2.12292045738e-10, "usdPrice": 7.18336841005e-15, "exchangeLogId": 5647508, "created": 1544499316000, "bestPair": "ltc", "sellTotalBtc": 5.31864201626, "volume": 0.0, "activePairs": "ltc", "sellTotal": 1380832406.65, "volumeBtc": 0.0, "buyTotalBtc": 0.325730123679, "coinId": 52}, {"buyBook": "[]", "exchangeId": 4, "sellBook": "[]", "updated": 1544499677000, "buyTotal": 10315581.7213, "satoshiPrice": 9e-08, "usdPrice": 3.049146e-12, "exchangeLogId": 5647620, "created": 1544499677000, "bestPair": "btc", "sellTotalBtc": 0.529073139345, "volume": 0.0, "activePairs": "btc", "sellTotal": 3148603.44061, "volumeBtc": 0.05129517, "buyTotalBtc": 0.313134808219, "coinId": 54}, {"buyBook": "[]", "exchangeId": 17, "sellBook": "[]", "updated": 1544499679000, "buyTotal": 0.0, "satoshiPrice": 0.0, "usdPrice": 0.0, "exchangeLogId": 5647621, "created": 1544499679000, "bestPair": "btc", "sellTotalBtc": 0.00224886703213, "volume": 0.0, "activePairs": "btc", "sellTotal": 224.4506363, "volumeBtc": 0.0, "buyTotalBtc": 0.0, "coinId": 54}, {"buyBook": "[]", "exchangeId": 22, "sellBook": "[]", "updated": 1544499211000, "buyTotal": 0.0, "satoshiPrice": 0.0, "usdPrice": 0.0, "exchangeLogId": 5647501, "created": 1544499211000, "bestPair": "", "sellTotalBtc": 240.25325761, "volume": 0.0, "activePairs": "", "sellTotal": 37607332.9088, "volumeBtc": 0.0, "buyTotalBtc": 0.0, "coinId": 57}, {"buyBook": "[]", "exchangeId": 4, "sellBook": "[]", "updated": 1544499441000, "buyTotal": 1401340823.33, "satoshiPrice": 3.53870446386e-10, "usdPrice": 1.19889184013e-14, "exchangeLogId": 5647552, "created": 1544499441000, "bestPair": "ltc", "sellTotalBtc": 3.89364560667, "volume": 0.0, "activePairs": "ltc", "sellTotal": 1078504143.98, "volumeBtc": 0.0, "buyTotalBtc": 0.423087776794, "coinId": 58}, {"buyBook": "[]", "exchangeId": 12, "sellBook": "[]", "updated": 1544499442000, "buyTotal": 2107802121.36, "satoshiPrice": 4e-10, "usdPrice": 1.355176e-14, "exchangeLogId": 5647553, "created": 1544499442000, "bestPair": "btc", "sellTotalBtc": 472189704.255, "volume": 0.0, "activePairs": "btc", "sellTotal": 3858718888.05, "volumeBtc": 0.04708183273229071, "buyTotalBtc": 0.710232323509, "coinId": 58}, {"buyBook": "[]", "exchangeId": 17, "sellBook": "[]", "updated": 1544499443000, "buyTotal": 0.0, "satoshiPrice": 0.0, "usdPrice": 0.0, "exchangeLogId": 5647554, "created": 1544499443000, "bestPair": "btc", "sellTotalBtc": 1e+24, "volume": 0.0, "activePairs": "btc", "sellTotal": 49441342.2195, "volumeBtc": 0.0, "buyTotalBtc": 0.0, "coinId": 58}, {"buyBook": "[]", "exchangeId": 22, "sellBook": "[]", "updated": 1544499447000, "buyTotal": 137438.0, "satoshiPrice": 0.0, "usdPrice": 0.0, "exchangeLogId": 5647555, "created": 1544499447000, "bestPair": "XMR", "sellTotalBtc": 69.8835922, "volume": 0.0, "activePairs": "XMR", "sellTotal": 9887963.0, "volumeBtc": 0.0, "buyTotalBtc": 0.00137438, "coinId": 58}, {"buyBook": "[]", "exchangeId": 5, "sellBook": "[]", "updated": 1544497188000, "buyTotal": 0.0, "satoshiPrice": 0.0, "usdPrice": 0.0, "exchangeLogId": 5647112, "created": 1544497188000, "bestPair": "btc", "sellTotalBtc": 0.0, "volume": 0.0033, "activePairs": "btc", "sellTotal": 0.0, "volumeBtc": 0.0, "buyTotalBtc": 0.0, "coinId": 61}, {"buyBook": "[]", "exchangeId": 22, "sellBook": "[]", "updated": 1544499149000, "buyTotal": 5093.69, "satoshiPrice": 3e-06, "usdPrice": 1.015116e-10, "exchangeLogId": 5647473, "created": 1544499149000, "bestPair": "BTC", "sellTotalBtc": 1002.75761152, "volume": 0.0, "activePairs": "BTC", "sellTotal": 7560.6054, "volumeBtc": 0.0, "buyTotalBtc": 0.00063317, "coinId": 61}, {"buyBook": "[]", "exchangeId": 26, "sellBook": "[]", "updated": 1544499149000, "buyTotal": 0.0, "satoshiPrice": 6e-06, "usdPrice": 2.030232e-10, "exchangeLogId": 5647474, "created": 1544499149000, "bestPair": "btc", "sellTotalBtc": 0.0, "volume": 0.0, "activePairs": "btc", "sellTotal": 0.0, "volumeBtc": 0.0, "buyTotalBtc": 0.0, "coinId": 61}, {"buyBook": "[]", "exchangeId": 4, "sellBook": "[]", "updated": 1544499314000, "buyTotal": 1106473.00785, "satoshiPrice": 2.09e-06, "usdPrice": 7.0719748e-11, "exchangeLogId": 5647506, "created": 1544499314000, "bestPair": "btc", "sellTotalBtc": 0.316318600151, "volume": 0.0, "activePairs": "btc", "sellTotal": 105347.416445, "volumeBtc": 0.07134238, "buyTotalBtc": 1.32160236489, "coinId": 67}, {"buyBook": "[]", "exchangeId": 25, "sellBook": "[]", "updated": 1544499315000, "buyTotal": 0.0, "satoshiPrice": 0.0, "usdPrice": 0.0, "exchangeLogId": 5647507, "created": 1544499315000, "bestPair": "", "sellTotalBtc": 0.00499999999997, "volume": 0.0, "activePairs": "btc", "sellTotal": 1190.47619047, "volumeBtc": 0.0, "buyTotalBtc": 0.0, "coinId": 67}, {"buyBook": "[]", "exchangeId": 12, "sellBook": "[]", "updated": 1544499707000, "buyTotal": 2604790.0, "satoshiPrice": 9e-08, "usdPrice": 3.049146e-12, "exchangeLogId": 5647628, "created": 1544499707000, "bestPair": "btc", "sellTotalBtc": 4615.59655091, "volume": 0.0, "activePairs": "btc", "sellTotal": 1729928.43717, "volumeBtc": 0.0065542968466149, "buyTotalBtc": 0.08120246, "coinId": 71}, {"buyBook": "[]", "exchangeId": 5, "sellBook": "[]", "updated": 1542754959000, "buyTotal": 1.5e-07, "satoshiPrice": 5e-08, "usdPrice": 2.128045e-12, "exchangeLogId": 4862160, "created": 1542754959000, "bestPair": "btc", "sellTotalBtc": 2.84511358, "volume": 0.0, "activePairs": "btc", "sellTotal": 0.00036572, "volumeBtc": 0.0, "buyTotalBtc": 0.07381892, "coinId": 74}, {"buyBook": "[]", "exchangeId": 5, "sellBook": "[]", "updated": 1544496928000, "buyTotal": 1.635e-05, "satoshiPrice": 7.9e-07, "usdPrice": 2.67731e-11, "exchangeLogId": 5647021, "created": 1544496928000, "bestPair": "btc", "sellTotalBtc": 1.71329494, "volume": 0.4486, "activePairs": "btc", "sellTotal": 0.00012349, "volumeBtc": 0.0, "buyTotalBtc": 0.45666371, "coinId": 75}, {"buyBook": "[]", "exchangeId": 4, "sellBook": "[]", "updated": 1544499624000, "buyTotal": 61403843.336, "satoshiPrice": 4e-08, "usdPrice": 1.355176e-12, "exchangeLogId": 5647601, "created": 1544499624000, "bestPair": "btc", "sellTotalBtc": 1.65224961074, "volume": 0.0, "activePairs": "btc", "sellTotal": 14140277.1761, "volumeBtc": 0.0, "buyTotalBtc": 0.694812902027, "coinId": 81}, {"buyBook": "[]", "exchangeId": 20, "sellBook": "[]", "updated": 1544499635000, "buyTotal": 0.0, "satoshiPrice": 0.0, "usdPrice": 0.0, "exchangeLogId": 5647602, "created": 1544499635000, "bestPair": "btc", "sellTotalBtc": 0.0, "volume": 0.0, "activePairs": "btc", "sellTotal": 0.0, "volumeBtc": 0.0, "buyTotalBtc": 0.0, "coinId": 81}, {"buyBook": "[]", "exchangeId": 4, "sellBook": "[]", "updated": 1544499422000, "buyTotal": 33428.6646919, "satoshiPrice": 7.32e-05, "usdPrice": 2.47997208e-09, "exchangeLogId": 5647543, "created": 1544499422000, "bestPair": "btc", "sellTotalBtc": 1.07909334621, "volume": 0.0, "activePairs": "btc", "sellTotal": 12876.0572116, "volumeBtc": 0.81977437, "buyTotalBtc": 0.140661011213, "coinId": 82}, {"buyBook": "[]", "exchangeId": 21, "sellBook": "[]", "updated": 1544499422000, "buyTotal": 734790.614602, "satoshiPrice": 6.518e-05, "usdPrice": 2.208259292e-09, "exchangeLogId": 5647544, "created": 1544499422000, "bestPair": "btc", "sellTotalBtc": 2.31478045579, "volume": 5013.09882355, "activePairs": "btc", "sellTotal": 27975.3260552, "volumeBtc": 0.33363548, "buyTotalBtc": 4.74987524294, "coinId": 82}, {"buyBook": "[]", "exchangeId": 17, "sellBook": "[]", "updated": 1544499644000, "buyTotal": 24251.47425, "satoshiPrice": 1e-08, "usdPrice": 3.38794e-13, "exchangeLogId": 5647611, "created": 1544499644000, "bestPair": "btc", "sellTotalBtc": 0.0447233088477, "volume": 0.0, "activePairs": "btc", "sellTotal": 999127.195881, "volumeBtc": 0.0, "buyTotalBtc": 0.0002425147425, "coinId": 84}, {"buyBook": "[]", "exchangeId": 4, "sellBook": "[]", "updated": 1544499174000, "buyTotal": 191868376.857, "satoshiPrice": 9.90696213446e-10, "usdPrice": 3.35223859136e-14, "exchangeLogId": 5647486, "created": 1544499174000, "bestPair": "ltc", "sellTotalBtc": 0.453611491239, "volume": 0.0, "activePairs": "ltc", "sellTotal": 64712821.6951, "volumeBtc": 0.0, "buyTotalBtc": 0.0691006998763, "coinId": 85}, {"buyBook": "[]", "exchangeId": 22, "sellBook": "[]", "updated": 1542755374000, "buyTotal": 3408.1, "satoshiPrice": 1e-07, "usdPrice": 4.1895e-12, "exchangeLogId": 4862324, "created": 1542755374000, "bestPair": "BTC", "sellTotalBtc": 0.04624735, "volume": 0.0, "activePairs": "BTC", "sellTotal": 4990.0, "volumeBtc": 0.0, "buyTotalBtc": 0.00033081, "coinId": 86}, {"buyBook": "[]", "exchangeId": 22, "sellBook": "[]", "updated": 1544499178000, "buyTotal": 52100.0, "satoshiPrice": 4e-08, "usdPrice": 1.353488e-12, "exchangeLogId": 5647487, "created": 1544499178000, "bestPair": "BTC", "sellTotalBtc": 2.10464628, "volume": 0.0, "activePairs": "BTC", "sellTotal": 198335.956522, "volumeBtc": 0.0, "buyTotalBtc": 0.001084, "coinId": 87}, {"buyBook": "[]", "exchangeId": 2, "sellBook": "[]", "updated": 1542755447000, "buyTotal": 0.0, "satoshiPrice": 0.0, "usdPrice": 0.0, "exchangeLogId": 4862359, "created": 1542755447000, "bestPair": "", "sellTotalBtc": 0.0, "volume": 0.0, "activePairs": "", "sellTotal": 0.0, "volumeBtc": 0.0, "buyTotalBtc": 0.0, "coinId": 88}, {"buyBook": "[]", "exchangeId": 11, "sellBook": "[]", "updated": 1544499441000, "buyTotal": 74565.0617531, "satoshiPrice": 0.00013816, "usdPrice": 4.680777904e-09, "exchangeLogId": 5647551, "created": 1544499441000, "bestPair": "btc", "sellTotalBtc": 191.159789771, "volume": 1463.5, "activePairs": "btc", "sellTotal": 161430.132136, "volumeBtc": 0.0, "buyTotalBtc": 7.05733616218, "coinId": 89}, {"buyBook": "[]", "exchangeId": 2, "sellBook": "[]", "updated": 1544499550000, "buyTotal": 933586793.849, "satoshiPrice": 1.89e-06, "usdPrice": 6.4032066e-11, "exchangeLogId": 5647573, "created": 1544499550000, "bestPair": "btc", "sellTotalBtc": 54.5945654578, "volume": 202242.895517, "activePairs": "btc,ltc,doge", "sellTotal": 353063.050667, "volumeBtc": 0.366301674851, "buyTotalBtc": 0.481813733758, "coinId": 91}, {"buyBook": "[]", "exchangeId": 12, "sellBook": "[]", "updated": 1544499551000, "buyTotal": 178347.899133, "satoshiPrice": 1.86e-06, "usdPrice": 6.3015684e-11, "exchangeLogId": 5647574, "created": 1544499551000, "bestPair": "btc", "sellTotalBtc": 0.163559193514, "volume": 0.0, "activePairs": "btc", "sellTotal": 1331.13186371, "volumeBtc": 0.000262945, "buyTotalBtc": 0.0240024945681, "coinId": 91}, {"buyBook": "[]", "exchangeId": 17, "sellBook": "[]", "updated": 1544499552000, "buyTotal": 0.0, "satoshiPrice": 0.0, "usdPrice": 0.0, "exchangeLogId": 5647575, "created": 1544499552000, "bestPair": "btc", "sellTotalBtc": 0.0, "volume": 0.0, "activePairs": "btc", "sellTotal": 0.0, "volumeBtc": 0.0, "buyTotalBtc": 0.0, "coinId": 91}, {"buyBook": "[]", "exchangeId": 22, "sellBook": "[]", "updated": 1544499811000, "buyTotal": 0.0, "satoshiPrice": 0.0, "usdPrice": 0.0, "exchangeLogId": 5647643, "created": 1544499811000, "bestPair": "", "sellTotalBtc": 0.0, "volume": 0.0, "activePairs": "", "sellTotal": 0.0, "volumeBtc": 0.0, "buyTotalBtc": 0.0, "coinId": 95}, {"buyBook": "[]", "exchangeId": 4, "sellBook": "[]", "updated": 1544499636000, "buyTotal": 255393822.49, "satoshiPrice": 1.19608210878e-08, "usdPrice": 4.05225441962e-13, "exchangeLogId": 5647603, "created": 1544499636000, "bestPair": "ltc", "sellTotalBtc": 1.54974485634, "volume": 0.0, "activePairs": "btc,ltc", "sellTotal": 50676491.8407, "volumeBtc": 0.0, "buyTotalBtc": 1.09457858552, "coinId": 96}, {"buyBook": "[]", "exchangeId": 12, "sellBook": "[]", "updated": 1544499637000, "buyTotal": 1855757.0, "satoshiPrice": 1e-08, "usdPrice": 3.38794e-13, "exchangeLogId": 5647604, "created": 1544499637000, "bestPair": "btc", "sellTotalBtc": 256342.540833, "volume": 0.0, "activePairs": "btc", "sellTotal": 8265541.67931, "volumeBtc": 7.6e-07, "buyTotalBtc": 0.01855757, "coinId": 96}, {"buyBook": "[]", "exchangeId": 17, "sellBook": "[]", "updated": 1544499638000, "buyTotal": 0.0, "satoshiPrice": 0.0, "usdPrice": 0.0, "exchangeLogId": 5647605, "created": 1544499638000, "bestPair": "btc", "sellTotalBtc": 0.0, "volume": 0.0, "activePairs": "btc", "sellTotal": 0.0, "volumeBtc": 0.0, "buyTotalBtc": 0.0, "coinId": 96}, {"buyBook": "[]", "exchangeId": 4, "sellBook": "[]", "updated": 1544499856000, "buyTotal": 1067237.57999, "satoshiPrice": 6.3e-07, "usdPrice": 2.1344022e-11, "exchangeLogId": 5647651, "created": 1544499856000, "bestPair": "btc", "sellTotalBtc": 0.566681883993, "volume": 0.0, "activePairs": "btc", "sellTotal": 569068.040666, "volumeBtc": 0.0560629, "buyTotalBtc": 0.356246035577, "coinId": 99}, {"buyBook": "[]", "exchangeId": 2, "sellBook": "[]", "updated": 1544499680000, "buyTotal": 622857.275817, "satoshiPrice": 7.031e-05, "usdPrice": 2.382060614e-09, "exchangeLogId": 5647622, "created": 1544499680000, "bestPair": "btc", "sellTotalBtc": 91.6665615702, "volume": 50593.3402206, "activePairs": "btc,ltc,doge", "sellTotal": 139644.01441, "volumeBtc": 3.59701379873, "buyTotalBtc": 4.35695144813, "coinId": 100}, {"buyBook": "[]", "exchangeId": 4, "sellBook": "[]", "updated": 1544499681000, "buyTotal": 78602.1593483, "satoshiPrice": 7.085e-05, "usdPrice": 2.40035549e-09, "exchangeLogId": 5647623, "created": 1544499681000, "bestPair": "btc", "sellTotalBtc": 1.36385991092, "volume": 0.0, "activePairs": "btc", "sellTotal": 17689.8326408, "volumeBtc": 0.43590658, "buyTotalBtc": 2.49010005211, "coinId": 100}, {"buyBook": "[]", "exchangeId": 22, "sellBook": "[]", "updated": 1544499659000, "buyTotal": 0.0, "satoshiPrice": 0.0, "usdPrice": 0.0, "exchangeLogId": 5647618, "created": 1544499659000, "bestPair": "", "sellTotalBtc": 14.43369055, "volume": 0.0, "activePairs": "", "sellTotal": 4243.3, "volumeBtc": 0.0, "buyTotalBtc": 0.0, "coinId": 101}, {"buyBook": "[]", "exchangeId": 4, "sellBook": "[]", "updated": 1544499377000, "buyTotal": 347987.120677, "satoshiPrice": 1.65e-06, "usdPrice": 5.583138e-11, "exchangeLogId": 5647532, "created": 1544499377000, "bestPair": "btc", "sellTotalBtc": 0.225852463527, "volume": 0.0, "activePairs": "btc", "sellTotal": 72398.8820756, "volumeBtc": 0.02756224, "buyTotalBtc": 0.372439476742, "coinId": 103}, {"buyBook": "[]", "exchangeId": 17, "sellBook": "[]", "updated": 1544499600000, "buyTotal": 91328.2280604, "satoshiPrice": 5e-07, "usdPrice": 1.69397e-11, "exchangeLogId": 5647592, "created": 1544499600000, "bestPair": "btc", "sellTotalBtc": 0.0541355707, "volume": 0.0, "activePairs": "btc", "sellTotal": 1352.553, "volumeBtc": 0.0, "buyTotalBtc": 0.0025103236434, "coinId": 104}, {"buyBook": "[]", "exchangeId": 12, "sellBook": "[]", "updated": 1544499440000, "buyTotal": 303842475.968, "satoshiPrice": 2.5e-08, "usdPrice": 8.46985e-13, "exchangeLogId": 5647550, "created": 1544499440000, "bestPair": "btc", "sellTotalBtc": 674895516.34, "volume": 0.0, "activePairs": "btc", "sellTotal": 127475280.348, "volumeBtc": 49.48889271892993, "buyTotalBtc": 4.65695152149, "coinId": 105}, {"buyBook": "[]", "exchangeId": 22, "sellBook": "[]", "updated": 1544499814000, "buyTotal": 0.0, "satoshiPrice": 0.0, "usdPrice": 0.0, "exchangeLogId": 5647644, "created": 1544499814000, "bestPair": "", "sellTotalBtc": 1.07118316, "volume": 0.0, "activePairs": "", "sellTotal": 79302.0, "volumeBtc": 0.0, "buyTotalBtc": 0.0, "coinId": 107}, {"buyBook": "[]", "exchangeId": 26, "sellBook": "[]", "updated": 1544499814000, "buyTotal": 0.0, "satoshiPrice": 3e-08, "usdPrice": 1.016382e-12, "exchangeLogId": 5647645, "created": 1544499814000, "bestPair": "btc", "sellTotalBtc": 0.0, "volume": 0.0, "activePairs": "btc", "sellTotal": 0.0, "volumeBtc": 0.0, "buyTotalBtc": 0.0, "coinId": 107}, {"buyBook": "[]", "exchangeId": 22, "sellBook": "[]", "updated": 1544499757000, "buyTotal": 1205554.0, "satoshiPrice": 1e-08, "usdPrice": 3.38794e-13, "exchangeLogId": 5647636, "created": 1544499757000, "bestPair": "BTC", "sellTotalBtc": 3.83895675, "volume": 0.0, "activePairs": "BTC", "sellTotal": 850909.572222, "volumeBtc": 0.0, "buyTotalBtc": 0.01205554, "coinId": 112}, {"buyBook": "[]", "exchangeId": 5, "sellBook": "[]", "updated": 1544497109000, "buyTotal": 0.0, "satoshiPrice": 0.0, "usdPrice": 0.0, "exchangeLogId": 5647092, "created": 1544497109000, "bestPair": "btc", "sellTotalBtc": 0.0, "volume": 0.0013, "activePairs": "btc", "sellTotal": 0.0, "volumeBtc": 0.0, "buyTotalBtc": 0.0, "coinId": 112}, {"buyBook": "[]", "exchangeId": 5, "sellBook": "[]", "updated": 1544496895000, "buyTotal": 4.844e-05, "satoshiPrice": 6.04e-06, "usdPrice": 2.046956e-10, "exchangeLogId": 5647005, "created": 1544496895000, "bestPair": "btc", "sellTotalBtc": 0.20415764, "volume": 0.0, "activePairs": "btc", "sellTotal": 0.10045794, "volumeBtc": 0.0, "buyTotalBtc": 0.20722441, "coinId": 113}, {"buyBook": "[]", "exchangeId": 4, "sellBook": "[]", "updated": 1544499468000, "buyTotal": 186885.180942, "satoshiPrice": 6.55e-06, "usdPrice": 2.2191007e-10, "exchangeLogId": 5647559, "created": 1544499468000, "bestPair": "btc", "sellTotalBtc": 0.41352322409, "volume": 0.0, "activePairs": "btc", "sellTotal": 45333.354667, "volumeBtc": 0.06558657, "buyTotalBtc": 0.504147756262, "coinId": 113}, {"buyBook": "[]", "exchangeId": 17, "sellBook": "[]", "updated": 1544499604000, "buyTotal": 235115.843, "satoshiPrice": 4e-08, "usdPrice": 1.355176e-12, "exchangeLogId": 5647595, "created": 1544499604000, "bestPair": "btc", "sellTotalBtc": 1.487363306, "volume": 0.00013936628, "activePairs": "btc", "sellTotal": 26493.731, "volumeBtc": 0.0, "buyTotalBtc": 0.00550463372, "coinId": 116}, {"buyBook": "[]", "exchangeId": 4, "sellBook": "[]", "updated": 1544499596000, "buyTotal": 122588.103567, "satoshiPrice": 8.35e-06, "usdPrice": 2.8289299e-10, "exchangeLogId": 5647589, "created": 1544499596000, "bestPair": "btc", "sellTotalBtc": 0.497430107578, "volume": 0.0, "activePairs": "btc", "sellTotal": 36336.4346806, "volumeBtc": 0.48321361, "buyTotalBtc": 0.286026751582, "coinId": 120}, {"buyBook": "[]", "exchangeId": 7, "sellBook": "[]", "updated": 1544499597000, "buyTotal": 120086.084717, "satoshiPrice": 1.001e-05, "usdPrice": 3.39132794e-10, "exchangeLogId": 5647590, "created": 1544499597000, "bestPair": "btc", "sellTotalBtc": 116.337477097, "volume": 956.03495835, "activePairs": "btc", "sellTotal": 2185.40035958, "volumeBtc": 0.00900989, "buyTotalBtc": 0.0261733437313, "coinId": 120}, {"buyBook": "[]", "exchangeId": 20, "sellBook": "[]", "updated": 1544499602000, "buyTotal": 1335184.4488, "satoshiPrice": 2e-08, "usdPrice": 6.77588e-13, "exchangeLogId": 5647594, "created": 1544499602000, "bestPair": "btc", "sellTotalBtc": 29.4098868951, "volume": 0.0, "activePairs": "btc", "sellTotal": 932218.0007, "volumeBtc": 0.0, "buyTotalBtc": 0.0078986132439, "coinId": 125}, {"buyBook": "[]", "exchangeId": 22, "sellBook": "[]", "updated": 1544499880000, "buyTotal": 92587.0, "satoshiPrice": 1e-08, "usdPrice": 3.38794e-13, "exchangeLogId": 5647656, "created": 1544499880000, "bestPair": "BTC", "sellTotalBtc": 3.30718277, "volume": 0.0, "activePairs": "BTC", "sellTotal": 19344.1125943, "volumeBtc": 0.0, "buyTotalBtc": 0.00092587, "coinId": 130}, {"buyBook": "[]", "exchangeId": 2, "sellBook": "[]", "updated": 1544499893000, "buyTotal": 1279721.99531, "satoshiPrice": 2.138e-05, "usdPrice": 7.24341572e-10, "exchangeLogId": 5647661, "created": 1544499893000, "bestPair": "btc", "sellTotalBtc": 6.14307270322, "volume": 5357.7926156, "activePairs": "btc,ltc,doge", "sellTotal": 25038.6564109, "volumeBtc": 0.123254650678, "buyTotalBtc": 1.63409375119, "coinId": 131}, {"buyBook": "[]", "exchangeId": 4, "sellBook": "[]", "updated": 1544499894000, "buyTotal": 127568.356212, "satoshiPrice": 2.159e-05, "usdPrice": 7.31456246e-10, "exchangeLogId": 5647662, "created": 1544499894000, "bestPair": "btc", "sellTotalBtc": 1.08209001727, "volume": 0.0, "activePairs": "btc", "sellTotal": 34816.3353484, "volumeBtc": 0.4625194, "buyTotalBtc": 1.14728054842, "coinId": 131}, {"buyBook": "[]", "exchangeId": 17, "sellBook": "[]", "updated": 1544499895000, "buyTotal": 0.0, "satoshiPrice": 0.0, "usdPrice": 0.0, "exchangeLogId": 5647663, "created": 1544499895000, "bestPair": "btc", "sellTotalBtc": 0.00084513759758, "volume": 0.0, "activePairs": "btc", "sellTotal": 30.89614684, "volumeBtc": 0.0, "buyTotalBtc": 0.0, "coinId": 131}, {"buyBook": "[]", "exchangeId": 4, "sellBook": "[]", "updated": 1544499352000, "buyTotal": 4621.89509507, "satoshiPrice": 0.0001715, "usdPrice": 5.8030798e-09, "exchangeLogId": 5647522, "created": 1544499352000, "bestPair": "btc", "sellTotalBtc": 1.65048496557, "volume": 0.0, "activePairs": "btc", "sellTotal": 290.13968665, "volumeBtc": 0.0, "buyTotalBtc": 0.0195262620994, "coinId": 135}, {"buyBook": "[]", "exchangeId": 3, "sellBook": "[]", "updated": 1544499739000, "buyTotal": 580564.803332, "satoshiPrice": 3e-08, "usdPrice": 1.016382e-12, "exchangeLogId": 5647633, "created": 1544499739000, "bestPair": "btc", "sellTotalBtc": 0.511594819395, "volume": 1316.42862434, "activePairs": "btc", "sellTotal": 1455755.78743, "volumeBtc": 0.0, "buyTotalBtc": 0.0147161841, "coinId": 136}, {"buyBook": "[]", "exchangeId": 4, "sellBook": "[]", "updated": 1544499426000, "buyTotal": 175777.481385, "satoshiPrice": 1.97e-06, "usdPrice": 6.6742418e-11, "exchangeLogId": 5647547, "created": 1544499426000, "bestPair": "btc", "sellTotalBtc": 0.597283448923, "volume": 0.0, "activePairs": "btc", "sellTotal": 135798.537226, "volumeBtc": 0.02337566, "buyTotalBtc": 0.19678174078, "coinId": 137}, {"buyBook": "[]", "exchangeId": 12, "sellBook": "[]", "updated": 1544499427000, "buyTotal": 437993.0, "satoshiPrice": 2.11e-06, "usdPrice": 7.1485534e-11, "exchangeLogId": 5647548, "created": 1544499427000, "bestPair": "btc", "sellTotalBtc": 11582.6149649, "volume": 0.0, "activePairs": "btc", "sellTotal": 112311.87567, "volumeBtc": 0.0016466834365914, "buyTotalBtc": 0.0451286, "coinId": 137}, {"buyBook": "[]", "exchangeId": 5, "sellBook": "[]", "updated": 1544496915000, "buyTotal": 0.00020013, "satoshiPrice": 8.75e-06, "usdPrice": 2.965375e-10, "exchangeLogId": 5647012, "created": 1544496915000, "bestPair": "btc", "sellTotalBtc": 0.36688043, "volume": 0.1031, "activePairs": "btc", "sellTotal": 0.00061053, "volumeBtc": 0.0, "buyTotalBtc": 0.28855808, "coinId": 142}, {"buyBook": "[]", "exchangeId": 17, "sellBook": "[]", "updated": 1544499531000, "buyTotal": 189431.948997, "satoshiPrice": 1.87068612513e-07, "usdPrice": 6.33777235079e-12, "exchangeLogId": 5647565, "created": 1544499531000, "bestPair": "eth", "sellTotalBtc": 4000.50598099, "volume": 0.0, "activePairs": "btc,eth", "sellTotal": 10199.0, "volumeBtc": 0.0, "buyTotalBtc": 0.0297050357849, "coinId": 142}, {"buyBook": "[]", "exchangeId": 22, "sellBook": "[]", "updated": 1544499535000, "buyTotal": 842.0, "satoshiPrice": 2.4e-07, "usdPrice": 8.131056e-12, "exchangeLogId": 5647566, "created": 1544499535000, "bestPair": "BTC", "sellTotalBtc": 0.0, "volume": 0.0, "activePairs": "BTC", "sellTotal": 0.0, "volumeBtc": 0.0, "buyTotalBtc": 9.968e-05, "coinId": 142}, {"buyBook": "[]", "exchangeId": 25, "sellBook": "[]", "updated": 1544499536000, "buyTotal": 0.0, "satoshiPrice": 0.0, "usdPrice": 0.0, "exchangeLogId": 5647567, "created": 1544499536000, "bestPair": "", "sellTotalBtc": 0.0, "volume": 0.0, "activePairs": "btc", "sellTotal": 0.0, "volumeBtc": 0.0, "buyTotalBtc": 0.0, "coinId": 142}, {"buyBook": "[]", "exchangeId": 21, "sellBook": "[]", "updated": 1544499968000, "buyTotal": 104901735.623, "satoshiPrice": 3.3e-07, "usdPrice": 1.1180202e-11, "exchangeLogId": 5647697, "created": 1544499968000, "bestPair": "btc", "sellTotalBtc": 60.357459562, "volume": 9137990.21005, "activePairs": "btc", "sellTotal": 101183162.848, "volumeBtc": 3.08778854, "buyTotalBtc": 12.6897009751, "coinId": 145}, {"buyBook": "[]", "exchangeId": 22, "sellBook": "[]", "updated": 1542754871000, "buyTotal": 0.0, "satoshiPrice": 0.0, "usdPrice": 0.0, "exchangeLogId": 4862114, "created": 1542754871000, "bestPair": "", "sellTotalBtc": 2.56807021, "volume": 0.0, "activePairs": "", "sellTotal": 61828.4988236, "volumeBtc": 0.0, "buyTotalBtc": 0.0, "coinId": 147}, {"buyBook": "[]", "exchangeId": 12, "sellBook": "[]", "updated": 1544499944000, "buyTotal": 8678108.0, "satoshiPrice": 1.76e-06, "usdPrice": 5.9627744e-11, "exchangeLogId": 5647688, "created": 1544499944000, "bestPair": "btc", "sellTotalBtc": 9.12057404918, "volume": 0.0, "activePairs": "btc", "sellTotal": 26723.3637733, "volumeBtc": 0.0065387439560423, "buyTotalBtc": 0.10910674, "coinId": 148}, {"buyBook": "[]", "exchangeId": 4, "sellBook": "[]", "updated": 1544499380000, "buyTotal": 449134.999663, "satoshiPrice": 6.5e-07, "usdPrice": 2.199418e-11, "exchangeLogId": 5647534, "created": 1544499380000, "bestPair": "btc", "sellTotalBtc": 0.647921236524, "volume": 0.0, "activePairs": "btc", "sellTotal": 454253.402839, "volumeBtc": 0.00095999, "buyTotalBtc": 0.152147751713, "coinId": 152}, {"buyBook": "[]", "exchangeId": 22, "sellBook": "[]", "updated": 1544499382000, "buyTotal": 0.0, "satoshiPrice": 0.0, "usdPrice": 0.0, "exchangeLogId": 5647535, "created": 1544499382000, "bestPair": "", "sellTotalBtc": 0.0, "volume": 0.0, "activePairs": "", "sellTotal": 0.0, "volumeBtc": 0.0, "buyTotalBtc": 0.0, "coinId": 152}, {"buyBook": "[]", "exchangeId": 5, "sellBook": "[]", "updated": 1544497122000, "buyTotal": 0.0, "satoshiPrice": 0.0, "usdPrice": 0.0, "exchangeLogId": 5647094, "created": 1544497122000, "bestPair": "btc", "sellTotalBtc": 0.0, "volume": 0.0, "activePairs": "btc", "sellTotal": 0.0, "volumeBtc": 0.0, "buyTotalBtc": 0.0, "coinId": 153}, {"buyBook": "[]", "exchangeId": 16, "sellBook": "[]", "updated": 1544499567000, "buyTotal": 0.0, "satoshiPrice": 0.0, "usdPrice": 0.0, "exchangeLogId": 5647580, "created": 1544499567000, "bestPair": "btc", "sellTotalBtc": 0.0, "volume": 0.0, "activePairs": "btc", "sellTotal": 0.0, "volumeBtc": 0.0, "buyTotalBtc": 0.0, "coinId": 155}, {"buyBook": "[]", "exchangeId": 22, "sellBook": "[]", "updated": 1544499743000, "buyTotal": 105625.0, "satoshiPrice": 1e-08, "usdPrice": 3.38794e-13, "exchangeLogId": 5647634, "created": 1544499743000, "bestPair": "BTC", "sellTotalBtc": 2.63015047, "volume": 0.0, "activePairs": "BTC", "sellTotal": 2238485.0, "volumeBtc": 0.00054375, "buyTotalBtc": 0.00105625, "coinId": 156}, {"buyBook": "[]", "exchangeId": 23, "sellBook": "[]", "updated": 1544499744000, "buyTotal": 0.0, "satoshiPrice": 7.07740892772e-10, "usdPrice": 2.39778368026e-14, "exchangeLogId": 5647635, "created": 1544499744000, "bestPair": "ltc", "sellTotalBtc": 0.0, "volume": 0.0, "activePairs": "btc,ltc", "sellTotal": 0.0, "volumeBtc": 0.0, "buyTotalBtc": 0.0, "coinId": 156}, {"buyBook": "[]", "exchangeId": 22, "sellBook": "[]", "updated": 1544499874000, "buyTotal": 7361.70009963, "satoshiPrice": 3.03e-05, "usdPrice": 1.02654582e-09, "exchangeLogId": 5647654, "created": 1544499874000, "bestPair": "BTC", "sellTotalBtc": 1.86725534, "volume": 0.0, "activePairs": "BTC", "sellTotal": 1927.53843168, "volumeBtc": 0.00045168, "buyTotalBtc": 0.00988199, "coinId": 157}, {"buyBook": "[]", "exchangeId": 21, "sellBook": "[]", "updated": 1541451816000, "buyTotal": 44419.7695033, "satoshiPrice": 4.909e-05, "usdPrice": 3.140356026e-09, "exchangeLogId": 4296261, "created": 1541451816000, "bestPair": "btc", "sellTotalBtc": 7.52914005374, "volume": 121973.287874, "activePairs": "btc", "sellTotal": 128264.272842, "volumeBtc": 5.74369943, "buyTotalBtc": 1.98779064711, "coinId": 157}, {"buyBook": "[]", "exchangeId": 17, "sellBook": "[]", "updated": 1542754570000, "buyTotal": 0.0, "satoshiPrice": 0.0, "usdPrice": 0.0, "exchangeLogId": 4861976, "created": 1542754570000, "bestPair": "btc", "sellTotalBtc": 1.1265625, "volume": 0.0, "activePairs": "btc", "sellTotal": 1000.0, "volumeBtc": 0.0, "buyTotalBtc": 0.0, "coinId": 159}, {"buyBook": "[]", "exchangeId": 20, "sellBook": "[]", "updated": 1542754572000, "buyTotal": 0.0, "satoshiPrice": 0.0, "usdPrice": 0.0, "exchangeLogId": 4861977, "created": 1542754572000, "bestPair": "btc", "sellTotalBtc": 11912.7940471, "volume": 0.0, "activePairs": "btc", "sellTotal": 34413894.3617, "volumeBtc": 0.0, "buyTotalBtc": 0.0, "coinId": 159}, {"buyBook": "[]", "exchangeId": 12, "sellBook": "[]", "updated": 1544499700000, "buyTotal": 67175.4080194, "satoshiPrice": 1.231e-05, "usdPrice": 4.17055414e-10, "exchangeLogId": 5647625, "created": 1544499700000, "bestPair": "btc", "sellTotalBtc": 11.674907821, "volume": 0.0, "activePairs": "btc", "sellTotal": 12497.4140207, "volumeBtc": 0.003201831, "buyTotalBtc": 0.0811853933184, "coinId": 168}, {"buyBook": "[]", "exchangeId": 17, "sellBook": "[]", "updated": 1544499702000, "buyTotal": 0.0, "satoshiPrice": 0.0, "usdPrice": 0.0, "exchangeLogId": 5647626, "created": 1544499702000, "bestPair": "btc", "sellTotalBtc": 0.0294808205154, "volume": 0.0, "activePairs": "btc", "sellTotal": 135.67371372, "volumeBtc": 0.0, "buyTotalBtc": 0.0, "coinId": 168}, {"buyBook": "[]", "exchangeId": 22, "sellBook": "[]", "updated": 1544499656000, "buyTotal": 217200.0, "satoshiPrice": 3e-08, "usdPrice": 1.016382e-12, "exchangeLogId": 5647617, "created": 1544499656000, "bestPair": "BTC", "sellTotalBtc": 22.65797419, "volume": 0.0, "activePairs": "BTC", "sellTotal": 550168.541438, "volumeBtc": 0.00078, "buyTotalBtc": 0.006516, "coinId": 169}, {"buyBook": "[]", "exchangeId": 22, "sellBook": "[]", "updated": 1544499706000, "buyTotal": 78138.0, "satoshiPrice": 5e-07, "usdPrice": 1.69397e-11, "exchangeLogId": 5647627, "created": 1544499706000, "bestPair": "BTC", "sellTotalBtc": 0.82603525, "volume": 0.0, "activePairs": "BTC", "sellTotal": 68598.2662888, "volumeBtc": 0.003001, "buyTotalBtc": 0.017113, "coinId": 173}, {"buyBook": "[]", "exchangeId": 5, "sellBook": "[]", "updated": 1544497079000, "buyTotal": 0.0, "satoshiPrice": 0.0, "usdPrice": 0.0, "exchangeLogId": 5647083, "created": 1544497079000, "bestPair": "btc", "sellTotalBtc": 0.0, "volume": 0.0516, "activePairs": "btc", "sellTotal": 0.0, "volumeBtc": 0.0, "buyTotalBtc": 0.0, "coinId": 175}, {"buyBook": "[]", "exchangeId": 22, "sellBook": "[]", "updated": 1544499511000, "buyTotal": 25114.0, "satoshiPrice": 2.51e-06, "usdPrice": 8.5037294e-11, "exchangeLogId": 5647564, "created": 1544499511000, "bestPair": "BTC", "sellTotalBtc": 0.55253766, "volume": 0.0, "activePairs": "BTC", "sellTotal": 86884.2376563, "volumeBtc": 0.0159887, "buyTotalBtc": 0.02866406, "coinId": 176}, {"buyBook": "[]", "exchangeId": 2, "sellBook": "[]", "updated": 1544499952000, "buyTotal": 1743454038.91, "satoshiPrice": 1.97259410436e-09, "usdPrice": 6.68303046994e-14, "exchangeLogId": 5647692, "created": 1544499952000, "bestPair": "doge", "sellTotalBtc": 504.399171282, "volume": 402489510.708, "activePairs": "btc,ltc,doge", "sellTotal": 3100286687.78, "volumeBtc": 0.942962943902, "buyTotalBtc": 0.99237040469, "coinId": 178}, {"buyBook": "[]", "exchangeId": 7, "sellBook": "[]", "updated": 1544499963000, "buyTotal": 0.0, "satoshiPrice": 0.0, "usdPrice": 0.0, "exchangeLogId": 5647693, "created": 1544499963000, "bestPair": "btc", "sellTotalBtc": 10757.5610001, "volume": 1009.99000999, "activePairs": "btc", "sellTotal": 126161946.63, "volumeBtc": 1.01e-05, "buyTotalBtc": 0.0, "coinId": 178}, {"buyBook": "[]", "exchangeId": 22, "sellBook": "[]", "updated": 1544499966000, "buyTotal": 0.0, "satoshiPrice": 0.0, "usdPrice": 0.0, "exchangeLogId": 5647694, "created": 1544499966000, "bestPair": "", "sellTotalBtc": 1.04179698, "volume": 0.0, "activePairs": "", "sellTotal": 879948.0, "volumeBtc": 0.0, "buyTotalBtc": 0.0, "coinId": 178}, {"buyBook": "[]", "exchangeId": 5, "sellBook": "[]", "updated": 1544497170000, "buyTotal": 0.0, "satoshiPrice": 0.0, "usdPrice": 0.0, "exchangeLogId": 5647105, "created": 1544497170000, "bestPair": "btc", "sellTotalBtc": 0.0, "volume": 0.6082, "activePairs": "btc", "sellTotal": 0.0, "volumeBtc": 0.0, "buyTotalBtc": 0.0, "coinId": 179}, {"buyBook": "[]", "exchangeId": 22, "sellBook": "[]", "updated": 1544499840000, "buyTotal": 15952066.25, "satoshiPrice": 0.0, "usdPrice": 0.0, "exchangeLogId": 5647646, "created": 1544499840000, "bestPair": "", "sellTotalBtc": 6.72449291, "volume": 0.0, "activePairs": "", "sellTotal": 16599029.7026, "volumeBtc": 0.0, "buyTotalBtc": 0.40960265, "coinId": 179}, {"buyBook": "[]", "exchangeId": 23, "sellBook": "[]", "updated": 1544499841000, "buyTotal": 0.0, "satoshiPrice": 3e-08, "usdPrice": 1.016382e-12, "exchangeLogId": 5647647, "created": 1544499841000, "bestPair": "btc", "sellTotalBtc": 0.0, "volume": 0.0, "activePairs": "btc,ltc", "sellTotal": 0.0, "volumeBtc": 0.0, "buyTotalBtc": 0.0, "coinId": 179}, {"buyBook": "[]", "exchangeId": 17, "sellBook": "[]", "updated": 1544499424000, "buyTotal": 6572.425, "satoshiPrice": 1e-07, "usdPrice": 3.38794e-12, "exchangeLogId": 5647545, "created": 1544499424000, "bestPair": "btc", "sellTotalBtc": 5.25213672528, "volume": 0.0, "activePairs": "btc", "sellTotal": 7733.9939, "volumeBtc": 0.0, "buyTotalBtc": 0.0006572425, "coinId": 180}, {"buyBook": "[]", "exchangeId": 26, "sellBook": "[]", "updated": 1544499425000, "buyTotal": 0.0, "satoshiPrice": 5e-08, "usdPrice": 1.69397e-12, "exchangeLogId": 5647546, "created": 1544499425000, "bestPair": "btc", "sellTotalBtc": 0.0, "volume": 77.78, "activePairs": "btc", "sellTotal": 0.0, "volumeBtc": 0.0, "buyTotalBtc": 0.0, "coinId": 180}, {"buyBook": "[]", "exchangeId": 7, "sellBook": "[]", "updated": 1542754681000, "buyTotal": 562227.975654, "satoshiPrice": 8.5e-07, "usdPrice": 3.6176765e-11, "exchangeLogId": 4862015, "created": 1542754681000, "bestPair": "btc", "sellTotalBtc": 21836.6059674, "volume": 2491.87645172, "activePairs": "btc", "sellTotal": 749999.041456, "volumeBtc": 0.00211021, "buyTotalBtc": 0.127565380455, "coinId": 183}, {"buyBook": "[]", "exchangeId": 24, "sellBook": "[]", "updated": 1544499677000, "buyTotal": 0.0, "satoshiPrice": 1e-12, "usdPrice": 3.38794e-17, "exchangeLogId": 5647619, "created": 1544499677000, "bestPair": "btc", "sellTotalBtc": 0.0, "volume": 0.0, "activePairs": "btc", "sellTotal": 0.0, "volumeBtc": 0.0, "buyTotalBtc": 0.0, "coinId": 187}, {"buyBook": "[]", "exchangeId": 17, "sellBook": "[]", "updated": 1542401890000, "buyTotal": 4062536.27273, "satoshiPrice": 1e-08, "usdPrice": 5.50501e-13, "exchangeLogId": 4708775, "created": 1542401890000, "bestPair": "btc", "sellTotalBtc": 3.36492563466, "volume": 0.195460381006, "activePairs": "btc,eth", "sellTotal": 110697919.549, "volumeBtc": 0.0, "buyTotalBtc": 0.0157628953496, "coinId": 187}, {"buyBook": "[]", "exchangeId": 5, "sellBook": "[]", "updated": 1544497047000, "buyTotal": 0.0, "satoshiPrice": 0.0, "usdPrice": 0.0, "exchangeLogId": 5647071, "created": 1544497047000, "bestPair": "btc", "sellTotalBtc": 0.0, "volume": 0.0005, "activePairs": "btc", "sellTotal": 0.0, "volumeBtc": 0.0, "buyTotalBtc": 0.0, "coinId": 187}, {"buyBook": "[]", "exchangeId": 22, "sellBook": "[]", "updated": 1544499951000, "buyTotal": 650581.666667, "satoshiPrice": 3e-08, "usdPrice": 1.016382e-12, "exchangeLogId": 5647691, "created": 1544499951000, "bestPair": "BTC", "sellTotalBtc": 2.28467944, "volume": 0.0, "activePairs": "BTC", "sellTotal": 380479.030528, "volumeBtc": 0.0, "buyTotalBtc": 0.01271745, "coinId": 188}, {"buyBook": "[]", "exchangeId": 22, "sellBook": "[]", "updated": 1544500034000, "buyTotal": 95000.0, "satoshiPrice": 1.3e-07, "usdPrice": 4.404322e-12, "exchangeLogId": 5647720, "created": 1544500034000, "bestPair": "BTC", "sellTotalBtc": 1.1502352, "volume": 0.0, "activePairs": "BTC", "sellTotal": 48988.1331383, "volumeBtc": 0.0041, "buyTotalBtc": 0.0083, "coinId": 191}, {"buyBook": "[]", "exchangeId": 22, "sellBook": "[]", "updated": 1544499885000, "buyTotal": 0.0, "satoshiPrice": 0.0, "usdPrice": 0.0, "exchangeLogId": 5647657, "created": 1544499885000, "bestPair": "", "sellTotalBtc": 0.0, "volume": 0.0, "activePairs": "", "sellTotal": 0.0, "volumeBtc": 0.0, "buyTotalBtc": 0.0, "coinId": 197}, {"buyBook": "[]", "exchangeId": 23, "sellBook": "[]", "updated": 1544499539000, "buyTotal": 0.0, "satoshiPrice": 0.0, "usdPrice": 0.0, "exchangeLogId": 5647570, "created": 1544499539000, "bestPair": "btc", "sellTotalBtc": 0.0, "volume": 0.0, "activePairs": "btc,ltc", "sellTotal": 0.0, "volumeBtc": 0.0, "buyTotalBtc": 0.0, "coinId": 199}, {"buyBook": "[]", "exchangeId": 26, "sellBook": "[]", "updated": 1544499539000, "buyTotal": 0.0, "satoshiPrice": 0.0, "usdPrice": 0.0, "exchangeLogId": 5647571, "created": 1544499539000, "bestPair": "btc", "sellTotalBtc": 0.0, "volume": 119639.0, "activePairs": "btc", "sellTotal": 0.0, "volumeBtc": 0.0, "buyTotalBtc": 0.0, "coinId": 199}, {"buyBook": "[]", "exchangeId": 17, "sellBook": "[]", "updated": 1544499967000, "buyTotal": 49902.9840877, "satoshiPrice": 1e-08, "usdPrice": 3.38794e-13, "exchangeLogId": 5647695, "created": 1544499967000, "bestPair": "btc", "sellTotalBtc": 5.24407555135, "volume": 0.0, "activePairs": "btc", "sellTotal": 62458.0288698, "volumeBtc": 0.0, "buyTotalBtc": 0.000499029840877, "coinId": 200}, {"buyBook": "[]", "exchangeId": 2, "sellBook": "[]", "updated": 1544499466000, "buyTotal": 0.0, "satoshiPrice": 0.0, "usdPrice": 0.0, "exchangeLogId": 5647557, "created": 1544499466000, "bestPair": "", "sellTotalBtc": 0.0, "volume": 0.0, "activePairs": "", "sellTotal": 0.0, "volumeBtc": 0.0, "buyTotalBtc": 0.0, "coinId": 201}, {"buyBook": "[]", "exchangeId": 4, "sellBook": "[]", "updated": 1544500012000, "buyTotal": 94443.3547824, "satoshiPrice": 1.007e-05, "usdPrice": 3.41165558e-10, "exchangeLogId": 5647712, "created": 1544500012000, "bestPair": "btc", "sellTotalBtc": 1.47040260364, "volume": 0.0, "activePairs": "btc", "sellTotal": 113839.26898, "volumeBtc": 1.00560034, "buyTotalBtc": 0.880174035765, "coinId": 211}, {"buyBook": "[]", "exchangeId": 7, "sellBook": "[]", "updated": 1544499896000, "buyTotal": 3692856.4285, "satoshiPrice": 1.8e-06, "usdPrice": 6.098292e-11, "exchangeLogId": 5647664, "created": 1544499896000, "bestPair": "btc", "sellTotalBtc": 15200419.5744, "volume": 236444.554385, "activePairs": "btc", "sellTotal": 11707441.727, "volumeBtc": 0.42622196, "buyTotalBtc": 4.56158347807, "coinId": 212}, {"buyBook": "[]", "exchangeId": 5, "sellBook": "[]", "updated": 1544497262000, "buyTotal": 0.0, "satoshiPrice": 0.0, "usdPrice": 0.0, "exchangeLogId": 5647144, "created": 1544497262000, "bestPair": "btc", "sellTotalBtc": 0.0, "volume": 0.3851, "activePairs": "btc", "sellTotal": 0.0, "volumeBtc": 0.0, "buyTotalBtc": 0.0, "coinId": 213}, {"buyBook": "[]", "exchangeId": 12, "sellBook": "[]", "updated": 1544499940000, "buyTotal": 45016.0, "satoshiPrice": 1.45e-06, "usdPrice": 4.912513e-11, "exchangeLogId": 5647682, "created": 1544499940000, "bestPair": "btc", "sellTotalBtc": 80384.5833009, "volume": 0.0, "activePairs": "btc", "sellTotal": 19584.0909091, "volumeBtc": 0.0014221783935867, "buyTotalBtc": 0.01000963, "coinId": 213}, {"buyBook": "[]", "exchangeId": 24, "sellBook": "[]", "updated": 1544499940000, "buyTotal": 0.0, "satoshiPrice": 7.2e-07, "usdPrice": 2.4393168e-11, "exchangeLogId": 5647683, "created": 1544499940000, "bestPair": "btc", "sellTotalBtc": 0.0, "volume": 0.0, "activePairs": "btc", "sellTotal": 0.0, "volumeBtc": 0.0, "buyTotalBtc": 0.0, "coinId": 213}, {"buyBook": "[]", "exchangeId": 26, "sellBook": "[]", "updated": 1544499940000, "buyTotal": 0.0, "satoshiPrice": 8.1e-07, "usdPrice": 2.7442314e-11, "exchangeLogId": 5647684, "created": 1544499940000, "bestPair": "btc", "sellTotalBtc": 0.0, "volume": 0.0, "activePairs": "btc", "sellTotal": 0.0, "volumeBtc": 0.0, "buyTotalBtc": 0.0, "coinId": 213}, {"buyBook": "[]", "exchangeId": 22, "sellBook": "[]", "updated": 1544499502000, "buyTotal": 291160.0, "satoshiPrice": 5e-08, "usdPrice": 1.69397e-12, "exchangeLogId": 5647561, "created": 1544499502000, "bestPair": "BTC", "sellTotalBtc": 70.86276641, "volume": 0.0, "activePairs": "BTC", "sellTotal": 141122.6, "volumeBtc": 0.0, "buyTotalBtc": 0.005302, "coinId": 216}, {"buyBook": "[]", "exchangeId": 22, "sellBook": "[]", "updated": 1544500040000, "buyTotal": 218923.000042, "satoshiPrice": 3.1e-06, "usdPrice": 1.0502614e-10, "exchangeLogId": 5647721, "created": 1544500040000, "bestPair": "BTC", "sellTotalBtc": 12068.7554603, "volume": 0.0, "activePairs": "BTC", "sellTotal": 290701.995919, "volumeBtc": 0.08438989, "buyTotalBtc": 0.28346253, "coinId": 217}, {"buyBook": "[]", "exchangeId": 7, "sellBook": "[]", "updated": 1544499600000, "buyTotal": 50745444.4577, "satoshiPrice": 1e-08, "usdPrice": 3.38794e-13, "exchangeLogId": 5647593, "created": 1544499600000, "bestPair": "btc", "sellTotalBtc": 300.847725436, "volume": 3636100.531, "activePairs": "btc", "sellTotal": 93358437.2103, "volumeBtc": 0.03706861, "buyTotalBtc": 0.507454444577, "coinId": 219}, {"buyBook": "[]", "exchangeId": 22, "sellBook": "[]", "updated": 1544499623000, "buyTotal": 200332.0, "satoshiPrice": 1e-06, "usdPrice": 3.38794e-11, "exchangeLogId": 5647599, "created": 1544499623000, "bestPair": "BTC", "sellTotalBtc": 2.05921819, "volume": 0.0, "activePairs": "BTC", "sellTotal": 6897.9946858, "volumeBtc": 0.004868, "buyTotalBtc": 0.020332, "coinId": 221}, {"buyBook": "[]", "exchangeId": 24, "sellBook": "[]", "updated": 1544499623000, "buyTotal": 0.0, "satoshiPrice": 4e-06, "usdPrice": 1.355176e-10, "exchangeLogId": 5647600, "created": 1544499623000, "bestPair": "btc", "sellTotalBtc": 0.0, "volume": 0.0, "activePairs": "btc", "sellTotal": 0.0, "volumeBtc": 0.0, "buyTotalBtc": 0.0, "coinId": 221}, {"buyBook": "[]", "exchangeId": 22, "sellBook": "[]", "updated": 1544499505000, "buyTotal": 0.0, "satoshiPrice": 0.0, "usdPrice": 0.0, "exchangeLogId": 5647563, "created": 1544499505000, "bestPair": "", "sellTotalBtc": 0.0, "volume": 0.0, "activePairs": "", "sellTotal": 0.0, "volumeBtc": 0.0, "buyTotalBtc": 0.0, "coinId": 229}, {"buyBook": "[]", "exchangeId": 26, "sellBook": "[]", "updated": 1544499968000, "buyTotal": 0.0, "satoshiPrice": 5.4e-07, "usdPrice": 1.8294876e-11, "exchangeLogId": 5647696, "created": 1544499968000, "bestPair": "btc", "sellTotalBtc": 0.0, "volume": 36.84, "activePairs": "btc", "sellTotal": 0.0, "volumeBtc": 0.0, "buyTotalBtc": 0.0, "coinId": 231}, {"buyBook": "[]", "exchangeId": 26, "sellBook": "[]", "updated": 1544499930000, "buyTotal": 0.0, "satoshiPrice": 3e-08, "usdPrice": 1.016382e-12, "exchangeLogId": 5647681, "created": 1544499930000, "bestPair": "btc", "sellTotalBtc": 0.0, "volume": 3719.9995, "activePairs": "btc", "sellTotal": 0.0, "volumeBtc": 0.0, "buyTotalBtc": 0.0, "coinId": 234}, {"buyBook": "[]", "exchangeId": 22, "sellBook": "[]", "updated": 1544499581000, "buyTotal": 0.0, "satoshiPrice": 0.0, "usdPrice": 0.0, "exchangeLogId": 5647582, "created": 1544499581000, "bestPair": "", "sellTotalBtc": 0.62557706, "volume": 0.0, "activePairs": "", "sellTotal": 29761309.4333, "volumeBtc": 0.0, "buyTotalBtc": 0.0, "coinId": 235}, {"buyBook": "[]", "exchangeId": 4, "sellBook": "[]", "updated": 1544500017000, "buyTotal": 7295101.64809, "satoshiPrice": 4.39e-06, "usdPrice": 1.48730566e-10, "exchangeLogId": 5647715, "created": 1544500017000, "bestPair": "btc", "sellTotalBtc": 1.13057474062, "volume": 0.0, "activePairs": "btc", "sellTotal": 199898.575391, "volumeBtc": 0.36620485, "buyTotalBtc": 0.788371962846, "coinId": 236}, {"buyBook": "[]", "exchangeId": 24, "sellBook": "[]", "updated": 1544500017000, "buyTotal": 0.0, "satoshiPrice": 0.0, "usdPrice": 0.0, "exchangeLogId": 5647716, "created": 1544500017000, "bestPair": "btc", "sellTotalBtc": 0.0, "volume": 0.0, "activePairs": "btc", "sellTotal": 0.0, "volumeBtc": 0.0, "buyTotalBtc": 0.0, "coinId": 236}, {"buyBook": "[]", "exchangeId": 4, "sellBook": "[]", "updated": 1544499682000, "buyTotal": 8224765.24196, "satoshiPrice": 3.1e-07, "usdPrice": 1.0502614e-11, "exchangeLogId": 5647624, "created": 1544499682000, "bestPair": "btc", "sellTotalBtc": 0.944709565337, "volume": 0.0, "activePairs": "btc", "sellTotal": 2406535.16384, "volumeBtc": 0.32752624, "buyTotalBtc": 2.17133541568, "coinId": 238}, {"buyBook": "[]", "exchangeId": 5, "sellBook": "[]", "updated": 1544497061000, "buyTotal": 0.0, "satoshiPrice": 0.0, "usdPrice": 0.0, "exchangeLogId": 5647078, "created": 1544497061000, "bestPair": "btc", "sellTotalBtc": 0.0, "volume": 0.0163, "activePairs": "btc", "sellTotal": 0.0, "volumeBtc": 0.0, "buyTotalBtc": 0.0, "coinId": 238}, {"buyBook": "[]", "exchangeId": 4, "sellBook": "[]", "updated": 1544499917000, "buyTotal": 0.0, "satoshiPrice": 0.0, "usdPrice": 0.0, "exchangeLogId": 5647672, "created": 1544499917000, "bestPair": "", "sellTotalBtc": 0.0, "volume": 0.0, "activePairs": "", "sellTotal": 0.0, "volumeBtc": 0.0, "buyTotalBtc": 0.0, "coinId": 245}, {"buyBook": "[]", "exchangeId": 12, "sellBook": "[]", "updated": 1544499918000, "buyTotal": 556056.0, "satoshiPrice": 6e-07, "usdPrice": 2.032764e-11, "exchangeLogId": 5647673, "created": 1544499918000, "bestPair": "btc", "sellTotalBtc": 0.2036784098, "volume": 0.0, "activePairs": "btc", "sellTotal": 59246.1318681, "volumeBtc": 0.0, "buyTotalBtc": 0.01476216, "coinId": 245}, {"buyBook": "[]", "exchangeId": 25, "sellBook": "[]", "updated": 1544499919000, "buyTotal": 0.0, "satoshiPrice": 0.0, "usdPrice": 0.0, "exchangeLogId": 5647674, "created": 1544499919000, "bestPair": "", "sellTotalBtc": 0.0, "volume": 0.0, "activePairs": "btc", "sellTotal": 0.0, "volumeBtc": 0.0, "buyTotalBtc": 0.0, "coinId": 245}]